[
    {
        "country": "AD",
        "hot dog": 48,
        "hot dogColor": "hsl(48, 70%, 50%)",
        "burger": 78,
        "burgerColor": "hsl(206, 70%, 50%)",
        "sandwich": 77,
        "sandwichColor": "hsl(7, 70%, 50%)",
        "kebab": 25,
        "kebabColor": "hsl(93, 70%, 50%)",
        "fries": 64,
        "friesColor": "hsl(15, 70%, 50%)",
        "donut": 98,
        "donutColor": "hsl(24, 70%, 50%)",
        "junk": 35,
        "junkColor": "hsl(127, 70%, 50%)",
        "sushi": 88,
        "sushiColor": "hsl(96, 70%, 50%)",
        "ramen": 82,
        "ramenColor": "hsl(112, 70%, 50%)",
        "curry": 25,
        "curryColor": "hsl(246, 70%, 50%)",
        "udon": 34,
        "udonColor": "hsl(125, 70%, 50%)",
        "bagel": 82,
        "bagelColor": "hsl(286, 70%, 50%)",
        "yakitori": 78,
        "yakitoriColor": "hsl(172, 70%, 50%)",
        "takoyaki": 84,
        "takoyakiColor": "hsl(132, 70%, 50%)",
        "tacos": 81,
        "tacosColor": "hsl(307, 70%, 50%)",
        "miso soup": 53,
        "miso soupColor": "hsl(67, 70%, 50%)",
        "tortilla": 62,
        "tortillaColor": "hsl(76, 70%, 50%)",
        "tapas": 36,
        "tapasColor": "hsl(260, 70%, 50%)",
        "chipirones": 32,
        "chipironesColor": "hsl(80, 70%, 50%)",
        "gazpacho": 82,
        "gazpachoColor": "hsl(335, 70%, 50%)",
        "soba": 28,
        "sobaColor": "hsl(337, 70%, 50%)",
        "bavette": 83,
        "bavetteColor": "hsl(359, 70%, 50%)",
        "steak": 51,
        "steakColor": "hsl(24, 70%, 50%)",
        "pizza": 41,
        "pizzaColor": "hsl(321, 70%, 50%)",
        "spaghetti": 5,
        "spaghettiColor": "hsl(76, 70%, 50%)",
        "ravioli": 85,
        "ravioliColor": "hsl(132, 70%, 50%)",
        "salad": 65,
        "saladColor": "hsl(248, 70%, 50%)",
        "pad thai": 40,
        "pad thaiColor": "hsl(121, 70%, 50%)",
        "bun": 84,
        "bunColor": "hsl(276, 70%, 50%)",
        "waffle": 73,
        "waffleColor": "hsl(325, 70%, 50%)",
        "crepe": 20,
        "crepeColor": "hsl(186, 70%, 50%)",
        "churros": 12,
        "churrosColor": "hsl(325, 70%, 50%)",
        "paella": 18,
        "paellaColor": "hsl(120, 70%, 50%)",
        "empanadas": 69,
        "empanadasColor": "hsl(341, 70%, 50%)",
        "bruschetta": 8,
        "bruschettaColor": "hsl(190, 70%, 50%)",
        "onion soup": 46,
        "onion soupColor": "hsl(228, 70%, 50%)",
        "cassoulet": 55,
        "cassouletColor": "hsl(330, 70%, 50%)",
        "bouillabaisse": 24,
        "bouillabaisseColor": "hsl(309, 70%, 50%)",
        "unagi": 94,
        "unagiColor": "hsl(320, 70%, 50%)",
        "tempura": 57,
        "tempuraColor": "hsl(212, 70%, 50%)",
        "tonkatsu": 93,
        "tonkatsuColor": "hsl(143, 70%, 50%)",
        "shabu-shabu": 96,
        "shabu-shabuColor": "hsl(319, 70%, 50%)",
        "twinkies": 81,
        "twinkiesColor": "hsl(48, 70%, 50%)",
        "jerky": 84,
        "jerkyColor": "hsl(137, 70%, 50%)",
        "fajitas": 88,
        "fajitasColor": "hsl(195, 70%, 50%)",
        "jambalaya": 99,
        "jambalayaColor": "hsl(260, 70%, 50%)",
        "meatloaf": 64,
        "meatloafColor": "hsl(197, 70%, 50%)",
        "mac n' cheese": 85,
        "mac n' cheeseColor": "hsl(115, 70%, 50%)",
        "baked beans": 68,
        "baked beansColor": "hsl(190, 70%, 50%)",
        "popcorn": 53,
        "popcornColor": "hsl(65, 70%, 50%)",
        "buffalo wings": 80,
        "buffalo wingsColor": "hsl(250, 70%, 50%)",
        "BBQ ribs": 68,
        "BBQ ribsColor": "hsl(267, 70%, 50%)",
        "apple pie": 59,
        "apple pieColor": "hsl(289, 70%, 50%)",
        "nachos": 88,
        "nachosColor": "hsl(261, 70%, 50%)",
        "risotto": 91,
        "risottoColor": "hsl(282, 70%, 50%)",
        "tiramisu": 98,
        "tiramisuColor": "hsl(139, 70%, 50%)"
    },
    {
        "country": "AE",
        "hot dog": 46,
        "hot dogColor": "hsl(117, 70%, 50%)",
        "burger": 7,
        "burgerColor": "hsl(295, 70%, 50%)",
        "sandwich": 92,
        "sandwichColor": "hsl(291, 70%, 50%)",
        "kebab": 61,
        "kebabColor": "hsl(31, 70%, 50%)",
        "fries": 62,
        "friesColor": "hsl(237, 70%, 50%)",
        "donut": 8,
        "donutColor": "hsl(25, 70%, 50%)",
        "junk": 31,
        "junkColor": "hsl(176, 70%, 50%)",
        "sushi": 7,
        "sushiColor": "hsl(227, 70%, 50%)",
        "ramen": 22,
        "ramenColor": "hsl(185, 70%, 50%)",
        "curry": 10,
        "curryColor": "hsl(200, 70%, 50%)",
        "udon": 61,
        "udonColor": "hsl(85, 70%, 50%)",
        "bagel": 47,
        "bagelColor": "hsl(92, 70%, 50%)",
        "yakitori": 79,
        "yakitoriColor": "hsl(9, 70%, 50%)",
        "takoyaki": 21,
        "takoyakiColor": "hsl(317, 70%, 50%)",
        "tacos": 27,
        "tacosColor": "hsl(270, 70%, 50%)",
        "miso soup": 77,
        "miso soupColor": "hsl(107, 70%, 50%)",
        "tortilla": 53,
        "tortillaColor": "hsl(180, 70%, 50%)",
        "tapas": 88,
        "tapasColor": "hsl(6, 70%, 50%)",
        "chipirones": 42,
        "chipironesColor": "hsl(85, 70%, 50%)",
        "gazpacho": 69,
        "gazpachoColor": "hsl(191, 70%, 50%)",
        "soba": 95,
        "sobaColor": "hsl(116, 70%, 50%)",
        "bavette": 74,
        "bavetteColor": "hsl(241, 70%, 50%)",
        "steak": 76,
        "steakColor": "hsl(351, 70%, 50%)",
        "pizza": 47,
        "pizzaColor": "hsl(66, 70%, 50%)",
        "spaghetti": 19,
        "spaghettiColor": "hsl(308, 70%, 50%)",
        "ravioli": 87,
        "ravioliColor": "hsl(2, 70%, 50%)",
        "salad": 61,
        "saladColor": "hsl(117, 70%, 50%)",
        "pad thai": 75,
        "pad thaiColor": "hsl(64, 70%, 50%)",
        "bun": 12,
        "bunColor": "hsl(13, 70%, 50%)",
        "waffle": 87,
        "waffleColor": "hsl(358, 70%, 50%)",
        "crepe": 62,
        "crepeColor": "hsl(165, 70%, 50%)",
        "churros": 74,
        "churrosColor": "hsl(123, 70%, 50%)",
        "paella": 50,
        "paellaColor": "hsl(292, 70%, 50%)",
        "empanadas": 42,
        "empanadasColor": "hsl(239, 70%, 50%)",
        "bruschetta": 41,
        "bruschettaColor": "hsl(3, 70%, 50%)",
        "onion soup": 5,
        "onion soupColor": "hsl(106, 70%, 50%)",
        "cassoulet": 61,
        "cassouletColor": "hsl(51, 70%, 50%)",
        "bouillabaisse": 89,
        "bouillabaisseColor": "hsl(130, 70%, 50%)",
        "unagi": 71,
        "unagiColor": "hsl(97, 70%, 50%)",
        "tempura": 67,
        "tempuraColor": "hsl(10, 70%, 50%)",
        "tonkatsu": 56,
        "tonkatsuColor": "hsl(82, 70%, 50%)",
        "shabu-shabu": 62,
        "shabu-shabuColor": "hsl(50, 70%, 50%)",
        "twinkies": 41,
        "twinkiesColor": "hsl(189, 70%, 50%)",
        "jerky": 84,
        "jerkyColor": "hsl(246, 70%, 50%)",
        "fajitas": 98,
        "fajitasColor": "hsl(88, 70%, 50%)",
        "jambalaya": 20,
        "jambalayaColor": "hsl(63, 70%, 50%)",
        "meatloaf": 47,
        "meatloafColor": "hsl(303, 70%, 50%)",
        "mac n' cheese": 46,
        "mac n' cheeseColor": "hsl(251, 70%, 50%)",
        "baked beans": 84,
        "baked beansColor": "hsl(329, 70%, 50%)",
        "popcorn": 34,
        "popcornColor": "hsl(239, 70%, 50%)",
        "buffalo wings": 84,
        "buffalo wingsColor": "hsl(56, 70%, 50%)",
        "BBQ ribs": 46,
        "BBQ ribsColor": "hsl(347, 70%, 50%)",
        "apple pie": 92,
        "apple pieColor": "hsl(122, 70%, 50%)",
        "nachos": 81,
        "nachosColor": "hsl(89, 70%, 50%)",
        "risotto": 53,
        "risottoColor": "hsl(200, 70%, 50%)",
        "tiramisu": 76,
        "tiramisuColor": "hsl(93, 70%, 50%)"
    },
    {
        "country": "AF",
        "hot dog": 73,
        "hot dogColor": "hsl(310, 70%, 50%)",
        "burger": 84,
        "burgerColor": "hsl(276, 70%, 50%)",
        "sandwich": 65,
        "sandwichColor": "hsl(358, 70%, 50%)",
        "kebab": 55,
        "kebabColor": "hsl(25, 70%, 50%)",
        "fries": 81,
        "friesColor": "hsl(15, 70%, 50%)",
        "donut": 53,
        "donutColor": "hsl(302, 70%, 50%)",
        "junk": 45,
        "junkColor": "hsl(70, 70%, 50%)",
        "sushi": 59,
        "sushiColor": "hsl(245, 70%, 50%)",
        "ramen": 100,
        "ramenColor": "hsl(356, 70%, 50%)",
        "curry": 47,
        "curryColor": "hsl(279, 70%, 50%)",
        "udon": 69,
        "udonColor": "hsl(144, 70%, 50%)",
        "bagel": 72,
        "bagelColor": "hsl(83, 70%, 50%)",
        "yakitori": 36,
        "yakitoriColor": "hsl(237, 70%, 50%)",
        "takoyaki": 79,
        "takoyakiColor": "hsl(292, 70%, 50%)",
        "tacos": 94,
        "tacosColor": "hsl(7, 70%, 50%)",
        "miso soup": 13,
        "miso soupColor": "hsl(183, 70%, 50%)",
        "tortilla": 81,
        "tortillaColor": "hsl(90, 70%, 50%)",
        "tapas": 11,
        "tapasColor": "hsl(52, 70%, 50%)",
        "chipirones": 39,
        "chipironesColor": "hsl(36, 70%, 50%)",
        "gazpacho": 79,
        "gazpachoColor": "hsl(171, 70%, 50%)",
        "soba": 17,
        "sobaColor": "hsl(218, 70%, 50%)",
        "bavette": 16,
        "bavetteColor": "hsl(258, 70%, 50%)",
        "steak": 96,
        "steakColor": "hsl(348, 70%, 50%)",
        "pizza": 25,
        "pizzaColor": "hsl(181, 70%, 50%)",
        "spaghetti": 97,
        "spaghettiColor": "hsl(224, 70%, 50%)",
        "ravioli": 77,
        "ravioliColor": "hsl(59, 70%, 50%)",
        "salad": 52,
        "saladColor": "hsl(253, 70%, 50%)",
        "pad thai": 89,
        "pad thaiColor": "hsl(210, 70%, 50%)",
        "bun": 62,
        "bunColor": "hsl(267, 70%, 50%)",
        "waffle": 83,
        "waffleColor": "hsl(222, 70%, 50%)",
        "crepe": 20,
        "crepeColor": "hsl(244, 70%, 50%)",
        "churros": 46,
        "churrosColor": "hsl(59, 70%, 50%)",
        "paella": 41,
        "paellaColor": "hsl(254, 70%, 50%)",
        "empanadas": 53,
        "empanadasColor": "hsl(250, 70%, 50%)",
        "bruschetta": 37,
        "bruschettaColor": "hsl(71, 70%, 50%)",
        "onion soup": 39,
        "onion soupColor": "hsl(150, 70%, 50%)",
        "cassoulet": 49,
        "cassouletColor": "hsl(307, 70%, 50%)",
        "bouillabaisse": 16,
        "bouillabaisseColor": "hsl(314, 70%, 50%)",
        "unagi": 47,
        "unagiColor": "hsl(319, 70%, 50%)",
        "tempura": 60,
        "tempuraColor": "hsl(296, 70%, 50%)",
        "tonkatsu": 15,
        "tonkatsuColor": "hsl(257, 70%, 50%)",
        "shabu-shabu": 82,
        "shabu-shabuColor": "hsl(338, 70%, 50%)",
        "twinkies": 18,
        "twinkiesColor": "hsl(73, 70%, 50%)",
        "jerky": 34,
        "jerkyColor": "hsl(30, 70%, 50%)",
        "fajitas": 100,
        "fajitasColor": "hsl(160, 70%, 50%)",
        "jambalaya": 0,
        "jambalayaColor": "hsl(299, 70%, 50%)",
        "meatloaf": 50,
        "meatloafColor": "hsl(11, 70%, 50%)",
        "mac n' cheese": 70,
        "mac n' cheeseColor": "hsl(90, 70%, 50%)",
        "baked beans": 57,
        "baked beansColor": "hsl(79, 70%, 50%)",
        "popcorn": 90,
        "popcornColor": "hsl(219, 70%, 50%)",
        "buffalo wings": 85,
        "buffalo wingsColor": "hsl(232, 70%, 50%)",
        "BBQ ribs": 60,
        "BBQ ribsColor": "hsl(99, 70%, 50%)",
        "apple pie": 46,
        "apple pieColor": "hsl(147, 70%, 50%)",
        "nachos": 66,
        "nachosColor": "hsl(351, 70%, 50%)",
        "risotto": 27,
        "risottoColor": "hsl(119, 70%, 50%)",
        "tiramisu": 23,
        "tiramisuColor": "hsl(247, 70%, 50%)"
    },
    {
        "country": "AG",
        "hot dog": 80,
        "hot dogColor": "hsl(283, 70%, 50%)",
        "burger": 74,
        "burgerColor": "hsl(257, 70%, 50%)",
        "sandwich": 0,
        "sandwichColor": "hsl(282, 70%, 50%)",
        "kebab": 46,
        "kebabColor": "hsl(146, 70%, 50%)",
        "fries": 57,
        "friesColor": "hsl(317, 70%, 50%)",
        "donut": 27,
        "donutColor": "hsl(9, 70%, 50%)",
        "junk": 31,
        "junkColor": "hsl(278, 70%, 50%)",
        "sushi": 16,
        "sushiColor": "hsl(304, 70%, 50%)",
        "ramen": 12,
        "ramenColor": "hsl(198, 70%, 50%)",
        "curry": 44,
        "curryColor": "hsl(152, 70%, 50%)",
        "udon": 69,
        "udonColor": "hsl(335, 70%, 50%)",
        "bagel": 21,
        "bagelColor": "hsl(330, 70%, 50%)",
        "yakitori": 93,
        "yakitoriColor": "hsl(74, 70%, 50%)",
        "takoyaki": 92,
        "takoyakiColor": "hsl(1, 70%, 50%)",
        "tacos": 77,
        "tacosColor": "hsl(275, 70%, 50%)",
        "miso soup": 86,
        "miso soupColor": "hsl(119, 70%, 50%)",
        "tortilla": 38,
        "tortillaColor": "hsl(205, 70%, 50%)",
        "tapas": 24,
        "tapasColor": "hsl(281, 70%, 50%)",
        "chipirones": 45,
        "chipironesColor": "hsl(176, 70%, 50%)",
        "gazpacho": 49,
        "gazpachoColor": "hsl(220, 70%, 50%)",
        "soba": 6,
        "sobaColor": "hsl(38, 70%, 50%)",
        "bavette": 38,
        "bavetteColor": "hsl(208, 70%, 50%)",
        "steak": 51,
        "steakColor": "hsl(140, 70%, 50%)",
        "pizza": 31,
        "pizzaColor": "hsl(140, 70%, 50%)",
        "spaghetti": 26,
        "spaghettiColor": "hsl(157, 70%, 50%)",
        "ravioli": 9,
        "ravioliColor": "hsl(265, 70%, 50%)",
        "salad": 76,
        "saladColor": "hsl(134, 70%, 50%)",
        "pad thai": 40,
        "pad thaiColor": "hsl(223, 70%, 50%)",
        "bun": 30,
        "bunColor": "hsl(331, 70%, 50%)",
        "waffle": 58,
        "waffleColor": "hsl(291, 70%, 50%)",
        "crepe": 74,
        "crepeColor": "hsl(66, 70%, 50%)",
        "churros": 15,
        "churrosColor": "hsl(294, 70%, 50%)",
        "paella": 22,
        "paellaColor": "hsl(299, 70%, 50%)",
        "empanadas": 68,
        "empanadasColor": "hsl(245, 70%, 50%)",
        "bruschetta": 43,
        "bruschettaColor": "hsl(32, 70%, 50%)",
        "onion soup": 34,
        "onion soupColor": "hsl(302, 70%, 50%)",
        "cassoulet": 24,
        "cassouletColor": "hsl(201, 70%, 50%)",
        "bouillabaisse": 76,
        "bouillabaisseColor": "hsl(270, 70%, 50%)",
        "unagi": 76,
        "unagiColor": "hsl(194, 70%, 50%)",
        "tempura": 41,
        "tempuraColor": "hsl(220, 70%, 50%)",
        "tonkatsu": 33,
        "tonkatsuColor": "hsl(121, 70%, 50%)",
        "shabu-shabu": 99,
        "shabu-shabuColor": "hsl(134, 70%, 50%)",
        "twinkies": 97,
        "twinkiesColor": "hsl(266, 70%, 50%)",
        "jerky": 89,
        "jerkyColor": "hsl(338, 70%, 50%)",
        "fajitas": 29,
        "fajitasColor": "hsl(70, 70%, 50%)",
        "jambalaya": 88,
        "jambalayaColor": "hsl(179, 70%, 50%)",
        "meatloaf": 80,
        "meatloafColor": "hsl(226, 70%, 50%)",
        "mac n' cheese": 67,
        "mac n' cheeseColor": "hsl(231, 70%, 50%)",
        "baked beans": 24,
        "baked beansColor": "hsl(177, 70%, 50%)",
        "popcorn": 91,
        "popcornColor": "hsl(31, 70%, 50%)",
        "buffalo wings": 74,
        "buffalo wingsColor": "hsl(158, 70%, 50%)",
        "BBQ ribs": 74,
        "BBQ ribsColor": "hsl(127, 70%, 50%)",
        "apple pie": 71,
        "apple pieColor": "hsl(280, 70%, 50%)",
        "nachos": 55,
        "nachosColor": "hsl(94, 70%, 50%)",
        "risotto": 5,
        "risottoColor": "hsl(293, 70%, 50%)",
        "tiramisu": 65,
        "tiramisuColor": "hsl(113, 70%, 50%)"
    },
    {
        "country": "AI",
        "hot dog": 6,
        "hot dogColor": "hsl(52, 70%, 50%)",
        "burger": 59,
        "burgerColor": "hsl(299, 70%, 50%)",
        "sandwich": 51,
        "sandwichColor": "hsl(190, 70%, 50%)",
        "kebab": 70,
        "kebabColor": "hsl(286, 70%, 50%)",
        "fries": 97,
        "friesColor": "hsl(62, 70%, 50%)",
        "donut": 19,
        "donutColor": "hsl(120, 70%, 50%)",
        "junk": 70,
        "junkColor": "hsl(196, 70%, 50%)",
        "sushi": 65,
        "sushiColor": "hsl(107, 70%, 50%)",
        "ramen": 18,
        "ramenColor": "hsl(333, 70%, 50%)",
        "curry": 55,
        "curryColor": "hsl(270, 70%, 50%)",
        "udon": 71,
        "udonColor": "hsl(199, 70%, 50%)",
        "bagel": 77,
        "bagelColor": "hsl(7, 70%, 50%)",
        "yakitori": 60,
        "yakitoriColor": "hsl(34, 70%, 50%)",
        "takoyaki": 15,
        "takoyakiColor": "hsl(204, 70%, 50%)",
        "tacos": 38,
        "tacosColor": "hsl(294, 70%, 50%)",
        "miso soup": 17,
        "miso soupColor": "hsl(83, 70%, 50%)",
        "tortilla": 40,
        "tortillaColor": "hsl(89, 70%, 50%)",
        "tapas": 12,
        "tapasColor": "hsl(236, 70%, 50%)",
        "chipirones": 55,
        "chipironesColor": "hsl(146, 70%, 50%)",
        "gazpacho": 35,
        "gazpachoColor": "hsl(217, 70%, 50%)",
        "soba": 14,
        "sobaColor": "hsl(130, 70%, 50%)",
        "bavette": 23,
        "bavetteColor": "hsl(21, 70%, 50%)",
        "steak": 46,
        "steakColor": "hsl(124, 70%, 50%)",
        "pizza": 46,
        "pizzaColor": "hsl(18, 70%, 50%)",
        "spaghetti": 17,
        "spaghettiColor": "hsl(197, 70%, 50%)",
        "ravioli": 97,
        "ravioliColor": "hsl(293, 70%, 50%)",
        "salad": 80,
        "saladColor": "hsl(152, 70%, 50%)",
        "pad thai": 91,
        "pad thaiColor": "hsl(358, 70%, 50%)",
        "bun": 6,
        "bunColor": "hsl(176, 70%, 50%)",
        "waffle": 50,
        "waffleColor": "hsl(105, 70%, 50%)",
        "crepe": 2,
        "crepeColor": "hsl(317, 70%, 50%)",
        "churros": 18,
        "churrosColor": "hsl(4, 70%, 50%)",
        "paella": 100,
        "paellaColor": "hsl(1, 70%, 50%)",
        "empanadas": 29,
        "empanadasColor": "hsl(152, 70%, 50%)",
        "bruschetta": 47,
        "bruschettaColor": "hsl(331, 70%, 50%)",
        "onion soup": 23,
        "onion soupColor": "hsl(137, 70%, 50%)",
        "cassoulet": 18,
        "cassouletColor": "hsl(69, 70%, 50%)",
        "bouillabaisse": 35,
        "bouillabaisseColor": "hsl(38, 70%, 50%)",
        "unagi": 30,
        "unagiColor": "hsl(44, 70%, 50%)",
        "tempura": 8,
        "tempuraColor": "hsl(217, 70%, 50%)",
        "tonkatsu": 24,
        "tonkatsuColor": "hsl(109, 70%, 50%)",
        "shabu-shabu": 87,
        "shabu-shabuColor": "hsl(345, 70%, 50%)",
        "twinkies": 32,
        "twinkiesColor": "hsl(18, 70%, 50%)",
        "jerky": 43,
        "jerkyColor": "hsl(139, 70%, 50%)",
        "fajitas": 26,
        "fajitasColor": "hsl(320, 70%, 50%)",
        "jambalaya": 27,
        "jambalayaColor": "hsl(45, 70%, 50%)",
        "meatloaf": 16,
        "meatloafColor": "hsl(225, 70%, 50%)",
        "mac n' cheese": 15,
        "mac n' cheeseColor": "hsl(96, 70%, 50%)",
        "baked beans": 46,
        "baked beansColor": "hsl(66, 70%, 50%)",
        "popcorn": 24,
        "popcornColor": "hsl(19, 70%, 50%)",
        "buffalo wings": 65,
        "buffalo wingsColor": "hsl(324, 70%, 50%)",
        "BBQ ribs": 65,
        "BBQ ribsColor": "hsl(267, 70%, 50%)",
        "apple pie": 18,
        "apple pieColor": "hsl(271, 70%, 50%)",
        "nachos": 97,
        "nachosColor": "hsl(6, 70%, 50%)",
        "risotto": 61,
        "risottoColor": "hsl(240, 70%, 50%)",
        "tiramisu": 78,
        "tiramisuColor": "hsl(302, 70%, 50%)"
    },
    {
        "country": "AL",
        "hot dog": 82,
        "hot dogColor": "hsl(175, 70%, 50%)",
        "burger": 69,
        "burgerColor": "hsl(329, 70%, 50%)",
        "sandwich": 48,
        "sandwichColor": "hsl(204, 70%, 50%)",
        "kebab": 31,
        "kebabColor": "hsl(16, 70%, 50%)",
        "fries": 48,
        "friesColor": "hsl(313, 70%, 50%)",
        "donut": 97,
        "donutColor": "hsl(330, 70%, 50%)",
        "junk": 54,
        "junkColor": "hsl(119, 70%, 50%)",
        "sushi": 31,
        "sushiColor": "hsl(352, 70%, 50%)",
        "ramen": 29,
        "ramenColor": "hsl(301, 70%, 50%)",
        "curry": 0,
        "curryColor": "hsl(77, 70%, 50%)",
        "udon": 44,
        "udonColor": "hsl(268, 70%, 50%)",
        "bagel": 82,
        "bagelColor": "hsl(159, 70%, 50%)",
        "yakitori": 7,
        "yakitoriColor": "hsl(40, 70%, 50%)",
        "takoyaki": 80,
        "takoyakiColor": "hsl(296, 70%, 50%)",
        "tacos": 7,
        "tacosColor": "hsl(296, 70%, 50%)",
        "miso soup": 52,
        "miso soupColor": "hsl(318, 70%, 50%)",
        "tortilla": 59,
        "tortillaColor": "hsl(185, 70%, 50%)",
        "tapas": 91,
        "tapasColor": "hsl(297, 70%, 50%)",
        "chipirones": 39,
        "chipironesColor": "hsl(82, 70%, 50%)",
        "gazpacho": 28,
        "gazpachoColor": "hsl(288, 70%, 50%)",
        "soba": 38,
        "sobaColor": "hsl(73, 70%, 50%)",
        "bavette": 67,
        "bavetteColor": "hsl(285, 70%, 50%)",
        "steak": 46,
        "steakColor": "hsl(210, 70%, 50%)",
        "pizza": 64,
        "pizzaColor": "hsl(302, 70%, 50%)",
        "spaghetti": 44,
        "spaghettiColor": "hsl(219, 70%, 50%)",
        "ravioli": 89,
        "ravioliColor": "hsl(34, 70%, 50%)",
        "salad": 73,
        "saladColor": "hsl(190, 70%, 50%)",
        "pad thai": 58,
        "pad thaiColor": "hsl(333, 70%, 50%)",
        "bun": 88,
        "bunColor": "hsl(277, 70%, 50%)",
        "waffle": 14,
        "waffleColor": "hsl(56, 70%, 50%)",
        "crepe": 64,
        "crepeColor": "hsl(236, 70%, 50%)",
        "churros": 31,
        "churrosColor": "hsl(187, 70%, 50%)",
        "paella": 97,
        "paellaColor": "hsl(157, 70%, 50%)",
        "empanadas": 36,
        "empanadasColor": "hsl(194, 70%, 50%)",
        "bruschetta": 5,
        "bruschettaColor": "hsl(214, 70%, 50%)",
        "onion soup": 18,
        "onion soupColor": "hsl(159, 70%, 50%)",
        "cassoulet": 37,
        "cassouletColor": "hsl(214, 70%, 50%)",
        "bouillabaisse": 45,
        "bouillabaisseColor": "hsl(320, 70%, 50%)",
        "unagi": 9,
        "unagiColor": "hsl(323, 70%, 50%)",
        "tempura": 25,
        "tempuraColor": "hsl(250, 70%, 50%)",
        "tonkatsu": 33,
        "tonkatsuColor": "hsl(83, 70%, 50%)",
        "shabu-shabu": 79,
        "shabu-shabuColor": "hsl(325, 70%, 50%)",
        "twinkies": 47,
        "twinkiesColor": "hsl(328, 70%, 50%)",
        "jerky": 53,
        "jerkyColor": "hsl(223, 70%, 50%)",
        "fajitas": 77,
        "fajitasColor": "hsl(235, 70%, 50%)",
        "jambalaya": 67,
        "jambalayaColor": "hsl(18, 70%, 50%)",
        "meatloaf": 72,
        "meatloafColor": "hsl(228, 70%, 50%)",
        "mac n' cheese": 91,
        "mac n' cheeseColor": "hsl(44, 70%, 50%)",
        "baked beans": 95,
        "baked beansColor": "hsl(224, 70%, 50%)",
        "popcorn": 33,
        "popcornColor": "hsl(60, 70%, 50%)",
        "buffalo wings": 98,
        "buffalo wingsColor": "hsl(37, 70%, 50%)",
        "BBQ ribs": 40,
        "BBQ ribsColor": "hsl(134, 70%, 50%)",
        "apple pie": 92,
        "apple pieColor": "hsl(289, 70%, 50%)",
        "nachos": 23,
        "nachosColor": "hsl(84, 70%, 50%)",
        "risotto": 9,
        "risottoColor": "hsl(347, 70%, 50%)",
        "tiramisu": 48,
        "tiramisuColor": "hsl(234, 70%, 50%)"
    },
    {
        "country": "AM",
        "hot dog": 47,
        "hot dogColor": "hsl(262, 70%, 50%)",
        "burger": 52,
        "burgerColor": "hsl(325, 70%, 50%)",
        "sandwich": 28,
        "sandwichColor": "hsl(98, 70%, 50%)",
        "kebab": 14,
        "kebabColor": "hsl(270, 70%, 50%)",
        "fries": 39,
        "friesColor": "hsl(126, 70%, 50%)",
        "donut": 65,
        "donutColor": "hsl(47, 70%, 50%)",
        "junk": 71,
        "junkColor": "hsl(12, 70%, 50%)",
        "sushi": 96,
        "sushiColor": "hsl(92, 70%, 50%)",
        "ramen": 81,
        "ramenColor": "hsl(225, 70%, 50%)",
        "curry": 3,
        "curryColor": "hsl(357, 70%, 50%)",
        "udon": 58,
        "udonColor": "hsl(169, 70%, 50%)",
        "bagel": 73,
        "bagelColor": "hsl(242, 70%, 50%)",
        "yakitori": 93,
        "yakitoriColor": "hsl(64, 70%, 50%)",
        "takoyaki": 14,
        "takoyakiColor": "hsl(233, 70%, 50%)",
        "tacos": 69,
        "tacosColor": "hsl(209, 70%, 50%)",
        "miso soup": 12,
        "miso soupColor": "hsl(30, 70%, 50%)",
        "tortilla": 9,
        "tortillaColor": "hsl(105, 70%, 50%)",
        "tapas": 96,
        "tapasColor": "hsl(297, 70%, 50%)",
        "chipirones": 76,
        "chipironesColor": "hsl(25, 70%, 50%)",
        "gazpacho": 30,
        "gazpachoColor": "hsl(201, 70%, 50%)",
        "soba": 28,
        "sobaColor": "hsl(94, 70%, 50%)",
        "bavette": 72,
        "bavetteColor": "hsl(212, 70%, 50%)",
        "steak": 54,
        "steakColor": "hsl(291, 70%, 50%)",
        "pizza": 52,
        "pizzaColor": "hsl(115, 70%, 50%)",
        "spaghetti": 76,
        "spaghettiColor": "hsl(55, 70%, 50%)",
        "ravioli": 26,
        "ravioliColor": "hsl(215, 70%, 50%)",
        "salad": 46,
        "saladColor": "hsl(78, 70%, 50%)",
        "pad thai": 7,
        "pad thaiColor": "hsl(40, 70%, 50%)",
        "bun": 65,
        "bunColor": "hsl(148, 70%, 50%)",
        "waffle": 15,
        "waffleColor": "hsl(323, 70%, 50%)",
        "crepe": 56,
        "crepeColor": "hsl(10, 70%, 50%)",
        "churros": 19,
        "churrosColor": "hsl(301, 70%, 50%)",
        "paella": 10,
        "paellaColor": "hsl(255, 70%, 50%)",
        "empanadas": 20,
        "empanadasColor": "hsl(277, 70%, 50%)",
        "bruschetta": 5,
        "bruschettaColor": "hsl(217, 70%, 50%)",
        "onion soup": 25,
        "onion soupColor": "hsl(328, 70%, 50%)",
        "cassoulet": 49,
        "cassouletColor": "hsl(186, 70%, 50%)",
        "bouillabaisse": 12,
        "bouillabaisseColor": "hsl(261, 70%, 50%)",
        "unagi": 86,
        "unagiColor": "hsl(102, 70%, 50%)",
        "tempura": 34,
        "tempuraColor": "hsl(7, 70%, 50%)",
        "tonkatsu": 37,
        "tonkatsuColor": "hsl(30, 70%, 50%)",
        "shabu-shabu": 49,
        "shabu-shabuColor": "hsl(257, 70%, 50%)",
        "twinkies": 98,
        "twinkiesColor": "hsl(128, 70%, 50%)",
        "jerky": 67,
        "jerkyColor": "hsl(155, 70%, 50%)",
        "fajitas": 5,
        "fajitasColor": "hsl(55, 70%, 50%)",
        "jambalaya": 54,
        "jambalayaColor": "hsl(244, 70%, 50%)",
        "meatloaf": 27,
        "meatloafColor": "hsl(98, 70%, 50%)",
        "mac n' cheese": 88,
        "mac n' cheeseColor": "hsl(207, 70%, 50%)",
        "baked beans": 55,
        "baked beansColor": "hsl(334, 70%, 50%)",
        "popcorn": 18,
        "popcornColor": "hsl(74, 70%, 50%)",
        "buffalo wings": 95,
        "buffalo wingsColor": "hsl(325, 70%, 50%)",
        "BBQ ribs": 66,
        "BBQ ribsColor": "hsl(76, 70%, 50%)",
        "apple pie": 96,
        "apple pieColor": "hsl(121, 70%, 50%)",
        "nachos": 68,
        "nachosColor": "hsl(200, 70%, 50%)",
        "risotto": 98,
        "risottoColor": "hsl(298, 70%, 50%)",
        "tiramisu": 90,
        "tiramisuColor": "hsl(299, 70%, 50%)"
    },
    {
        "country": "AO",
        "hot dog": 99,
        "hot dogColor": "hsl(282, 70%, 50%)",
        "burger": 0,
        "burgerColor": "hsl(28, 70%, 50%)",
        "sandwich": 69,
        "sandwichColor": "hsl(359, 70%, 50%)",
        "kebab": 27,
        "kebabColor": "hsl(172, 70%, 50%)",
        "fries": 0,
        "friesColor": "hsl(11, 70%, 50%)",
        "donut": 38,
        "donutColor": "hsl(15, 70%, 50%)",
        "junk": 65,
        "junkColor": "hsl(282, 70%, 50%)",
        "sushi": 73,
        "sushiColor": "hsl(98, 70%, 50%)",
        "ramen": 25,
        "ramenColor": "hsl(114, 70%, 50%)",
        "curry": 82,
        "curryColor": "hsl(213, 70%, 50%)",
        "udon": 50,
        "udonColor": "hsl(7, 70%, 50%)",
        "bagel": 83,
        "bagelColor": "hsl(100, 70%, 50%)",
        "yakitori": 9,
        "yakitoriColor": "hsl(36, 70%, 50%)",
        "takoyaki": 68,
        "takoyakiColor": "hsl(349, 70%, 50%)",
        "tacos": 38,
        "tacosColor": "hsl(74, 70%, 50%)",
        "miso soup": 39,
        "miso soupColor": "hsl(15, 70%, 50%)",
        "tortilla": 98,
        "tortillaColor": "hsl(174, 70%, 50%)",
        "tapas": 11,
        "tapasColor": "hsl(190, 70%, 50%)",
        "chipirones": 61,
        "chipironesColor": "hsl(209, 70%, 50%)",
        "gazpacho": 84,
        "gazpachoColor": "hsl(294, 70%, 50%)",
        "soba": 95,
        "sobaColor": "hsl(242, 70%, 50%)",
        "bavette": 33,
        "bavetteColor": "hsl(216, 70%, 50%)",
        "steak": 87,
        "steakColor": "hsl(91, 70%, 50%)",
        "pizza": 18,
        "pizzaColor": "hsl(335, 70%, 50%)",
        "spaghetti": 49,
        "spaghettiColor": "hsl(159, 70%, 50%)",
        "ravioli": 25,
        "ravioliColor": "hsl(284, 70%, 50%)",
        "salad": 12,
        "saladColor": "hsl(165, 70%, 50%)",
        "pad thai": 81,
        "pad thaiColor": "hsl(36, 70%, 50%)",
        "bun": 36,
        "bunColor": "hsl(305, 70%, 50%)",
        "waffle": 42,
        "waffleColor": "hsl(67, 70%, 50%)",
        "crepe": 99,
        "crepeColor": "hsl(202, 70%, 50%)",
        "churros": 31,
        "churrosColor": "hsl(17, 70%, 50%)",
        "paella": 2,
        "paellaColor": "hsl(34, 70%, 50%)",
        "empanadas": 43,
        "empanadasColor": "hsl(163, 70%, 50%)",
        "bruschetta": 35,
        "bruschettaColor": "hsl(45, 70%, 50%)",
        "onion soup": 76,
        "onion soupColor": "hsl(186, 70%, 50%)",
        "cassoulet": 82,
        "cassouletColor": "hsl(110, 70%, 50%)",
        "bouillabaisse": 45,
        "bouillabaisseColor": "hsl(155, 70%, 50%)",
        "unagi": 67,
        "unagiColor": "hsl(146, 70%, 50%)",
        "tempura": 8,
        "tempuraColor": "hsl(49, 70%, 50%)",
        "tonkatsu": 8,
        "tonkatsuColor": "hsl(148, 70%, 50%)",
        "shabu-shabu": 90,
        "shabu-shabuColor": "hsl(112, 70%, 50%)",
        "twinkies": 58,
        "twinkiesColor": "hsl(13, 70%, 50%)",
        "jerky": 30,
        "jerkyColor": "hsl(62, 70%, 50%)",
        "fajitas": 0,
        "fajitasColor": "hsl(143, 70%, 50%)",
        "jambalaya": 16,
        "jambalayaColor": "hsl(214, 70%, 50%)",
        "meatloaf": 46,
        "meatloafColor": "hsl(316, 70%, 50%)",
        "mac n' cheese": 19,
        "mac n' cheeseColor": "hsl(179, 70%, 50%)",
        "baked beans": 9,
        "baked beansColor": "hsl(320, 70%, 50%)",
        "popcorn": 41,
        "popcornColor": "hsl(112, 70%, 50%)",
        "buffalo wings": 86,
        "buffalo wingsColor": "hsl(186, 70%, 50%)",
        "BBQ ribs": 18,
        "BBQ ribsColor": "hsl(285, 70%, 50%)",
        "apple pie": 30,
        "apple pieColor": "hsl(136, 70%, 50%)",
        "nachos": 49,
        "nachosColor": "hsl(191, 70%, 50%)",
        "risotto": 98,
        "risottoColor": "hsl(13, 70%, 50%)",
        "tiramisu": 85,
        "tiramisuColor": "hsl(18, 70%, 50%)"
    },
    {
        "country": "AQ",
        "hot dog": 14,
        "hot dogColor": "hsl(148, 70%, 50%)",
        "burger": 68,
        "burgerColor": "hsl(171, 70%, 50%)",
        "sandwich": 23,
        "sandwichColor": "hsl(185, 70%, 50%)",
        "kebab": 72,
        "kebabColor": "hsl(11, 70%, 50%)",
        "fries": 66,
        "friesColor": "hsl(327, 70%, 50%)",
        "donut": 19,
        "donutColor": "hsl(320, 70%, 50%)",
        "junk": 89,
        "junkColor": "hsl(34, 70%, 50%)",
        "sushi": 91,
        "sushiColor": "hsl(111, 70%, 50%)",
        "ramen": 68,
        "ramenColor": "hsl(216, 70%, 50%)",
        "curry": 24,
        "curryColor": "hsl(1, 70%, 50%)",
        "udon": 91,
        "udonColor": "hsl(212, 70%, 50%)",
        "bagel": 48,
        "bagelColor": "hsl(86, 70%, 50%)",
        "yakitori": 71,
        "yakitoriColor": "hsl(64, 70%, 50%)",
        "takoyaki": 64,
        "takoyakiColor": "hsl(349, 70%, 50%)",
        "tacos": 96,
        "tacosColor": "hsl(242, 70%, 50%)",
        "miso soup": 60,
        "miso soupColor": "hsl(119, 70%, 50%)",
        "tortilla": 41,
        "tortillaColor": "hsl(138, 70%, 50%)",
        "tapas": 59,
        "tapasColor": "hsl(270, 70%, 50%)",
        "chipirones": 30,
        "chipironesColor": "hsl(341, 70%, 50%)",
        "gazpacho": 25,
        "gazpachoColor": "hsl(331, 70%, 50%)",
        "soba": 13,
        "sobaColor": "hsl(239, 70%, 50%)",
        "bavette": 24,
        "bavetteColor": "hsl(204, 70%, 50%)",
        "steak": 89,
        "steakColor": "hsl(73, 70%, 50%)",
        "pizza": 84,
        "pizzaColor": "hsl(201, 70%, 50%)",
        "spaghetti": 62,
        "spaghettiColor": "hsl(144, 70%, 50%)",
        "ravioli": 18,
        "ravioliColor": "hsl(273, 70%, 50%)",
        "salad": 9,
        "saladColor": "hsl(298, 70%, 50%)",
        "pad thai": 14,
        "pad thaiColor": "hsl(153, 70%, 50%)",
        "bun": 26,
        "bunColor": "hsl(46, 70%, 50%)",
        "waffle": 72,
        "waffleColor": "hsl(120, 70%, 50%)",
        "crepe": 47,
        "crepeColor": "hsl(306, 70%, 50%)",
        "churros": 22,
        "churrosColor": "hsl(170, 70%, 50%)",
        "paella": 15,
        "paellaColor": "hsl(82, 70%, 50%)",
        "empanadas": 44,
        "empanadasColor": "hsl(52, 70%, 50%)",
        "bruschetta": 91,
        "bruschettaColor": "hsl(127, 70%, 50%)",
        "onion soup": 44,
        "onion soupColor": "hsl(91, 70%, 50%)",
        "cassoulet": 6,
        "cassouletColor": "hsl(47, 70%, 50%)",
        "bouillabaisse": 77,
        "bouillabaisseColor": "hsl(118, 70%, 50%)",
        "unagi": 44,
        "unagiColor": "hsl(36, 70%, 50%)",
        "tempura": 1,
        "tempuraColor": "hsl(25, 70%, 50%)",
        "tonkatsu": 54,
        "tonkatsuColor": "hsl(217, 70%, 50%)",
        "shabu-shabu": 90,
        "shabu-shabuColor": "hsl(183, 70%, 50%)",
        "twinkies": 76,
        "twinkiesColor": "hsl(286, 70%, 50%)",
        "jerky": 55,
        "jerkyColor": "hsl(82, 70%, 50%)",
        "fajitas": 75,
        "fajitasColor": "hsl(94, 70%, 50%)",
        "jambalaya": 33,
        "jambalayaColor": "hsl(43, 70%, 50%)",
        "meatloaf": 60,
        "meatloafColor": "hsl(173, 70%, 50%)",
        "mac n' cheese": 80,
        "mac n' cheeseColor": "hsl(174, 70%, 50%)",
        "baked beans": 84,
        "baked beansColor": "hsl(145, 70%, 50%)",
        "popcorn": 83,
        "popcornColor": "hsl(263, 70%, 50%)",
        "buffalo wings": 31,
        "buffalo wingsColor": "hsl(28, 70%, 50%)",
        "BBQ ribs": 70,
        "BBQ ribsColor": "hsl(74, 70%, 50%)",
        "apple pie": 27,
        "apple pieColor": "hsl(98, 70%, 50%)",
        "nachos": 54,
        "nachosColor": "hsl(337, 70%, 50%)",
        "risotto": 60,
        "risottoColor": "hsl(300, 70%, 50%)",
        "tiramisu": 22,
        "tiramisuColor": "hsl(83, 70%, 50%)"
    },
    {
        "country": "AR",
        "hot dog": 33,
        "hot dogColor": "hsl(94, 70%, 50%)",
        "burger": 14,
        "burgerColor": "hsl(328, 70%, 50%)",
        "sandwich": 0,
        "sandwichColor": "hsl(98, 70%, 50%)",
        "kebab": 59,
        "kebabColor": "hsl(205, 70%, 50%)",
        "fries": 61,
        "friesColor": "hsl(289, 70%, 50%)",
        "donut": 18,
        "donutColor": "hsl(248, 70%, 50%)",
        "junk": 27,
        "junkColor": "hsl(304, 70%, 50%)",
        "sushi": 73,
        "sushiColor": "hsl(177, 70%, 50%)",
        "ramen": 9,
        "ramenColor": "hsl(223, 70%, 50%)",
        "curry": 8,
        "curryColor": "hsl(110, 70%, 50%)",
        "udon": 58,
        "udonColor": "hsl(294, 70%, 50%)",
        "bagel": 26,
        "bagelColor": "hsl(100, 70%, 50%)",
        "yakitori": 25,
        "yakitoriColor": "hsl(139, 70%, 50%)",
        "takoyaki": 6,
        "takoyakiColor": "hsl(300, 70%, 50%)",
        "tacos": 5,
        "tacosColor": "hsl(332, 70%, 50%)",
        "miso soup": 18,
        "miso soupColor": "hsl(233, 70%, 50%)",
        "tortilla": 95,
        "tortillaColor": "hsl(39, 70%, 50%)",
        "tapas": 37,
        "tapasColor": "hsl(139, 70%, 50%)",
        "chipirones": 67,
        "chipironesColor": "hsl(102, 70%, 50%)",
        "gazpacho": 7,
        "gazpachoColor": "hsl(105, 70%, 50%)",
        "soba": 73,
        "sobaColor": "hsl(182, 70%, 50%)",
        "bavette": 13,
        "bavetteColor": "hsl(262, 70%, 50%)",
        "steak": 71,
        "steakColor": "hsl(183, 70%, 50%)",
        "pizza": 1,
        "pizzaColor": "hsl(72, 70%, 50%)",
        "spaghetti": 27,
        "spaghettiColor": "hsl(149, 70%, 50%)",
        "ravioli": 51,
        "ravioliColor": "hsl(317, 70%, 50%)",
        "salad": 93,
        "saladColor": "hsl(143, 70%, 50%)",
        "pad thai": 92,
        "pad thaiColor": "hsl(287, 70%, 50%)",
        "bun": 71,
        "bunColor": "hsl(161, 70%, 50%)",
        "waffle": 92,
        "waffleColor": "hsl(275, 70%, 50%)",
        "crepe": 10,
        "crepeColor": "hsl(230, 70%, 50%)",
        "churros": 75,
        "churrosColor": "hsl(354, 70%, 50%)",
        "paella": 5,
        "paellaColor": "hsl(180, 70%, 50%)",
        "empanadas": 30,
        "empanadasColor": "hsl(137, 70%, 50%)",
        "bruschetta": 43,
        "bruschettaColor": "hsl(246, 70%, 50%)",
        "onion soup": 27,
        "onion soupColor": "hsl(181, 70%, 50%)",
        "cassoulet": 62,
        "cassouletColor": "hsl(199, 70%, 50%)",
        "bouillabaisse": 79,
        "bouillabaisseColor": "hsl(247, 70%, 50%)",
        "unagi": 11,
        "unagiColor": "hsl(265, 70%, 50%)",
        "tempura": 87,
        "tempuraColor": "hsl(144, 70%, 50%)",
        "tonkatsu": 50,
        "tonkatsuColor": "hsl(44, 70%, 50%)",
        "shabu-shabu": 28,
        "shabu-shabuColor": "hsl(69, 70%, 50%)",
        "twinkies": 32,
        "twinkiesColor": "hsl(101, 70%, 50%)",
        "jerky": 85,
        "jerkyColor": "hsl(194, 70%, 50%)",
        "fajitas": 70,
        "fajitasColor": "hsl(137, 70%, 50%)",
        "jambalaya": 54,
        "jambalayaColor": "hsl(149, 70%, 50%)",
        "meatloaf": 57,
        "meatloafColor": "hsl(268, 70%, 50%)",
        "mac n' cheese": 98,
        "mac n' cheeseColor": "hsl(88, 70%, 50%)",
        "baked beans": 96,
        "baked beansColor": "hsl(37, 70%, 50%)",
        "popcorn": 64,
        "popcornColor": "hsl(86, 70%, 50%)",
        "buffalo wings": 7,
        "buffalo wingsColor": "hsl(306, 70%, 50%)",
        "BBQ ribs": 75,
        "BBQ ribsColor": "hsl(86, 70%, 50%)",
        "apple pie": 98,
        "apple pieColor": "hsl(324, 70%, 50%)",
        "nachos": 44,
        "nachosColor": "hsl(335, 70%, 50%)",
        "risotto": 72,
        "risottoColor": "hsl(133, 70%, 50%)",
        "tiramisu": 54,
        "tiramisuColor": "hsl(29, 70%, 50%)"
    },
    {
        "country": "AS",
        "hot dog": 7,
        "hot dogColor": "hsl(130, 70%, 50%)",
        "burger": 2,
        "burgerColor": "hsl(239, 70%, 50%)",
        "sandwich": 3,
        "sandwichColor": "hsl(345, 70%, 50%)",
        "kebab": 63,
        "kebabColor": "hsl(283, 70%, 50%)",
        "fries": 40,
        "friesColor": "hsl(160, 70%, 50%)",
        "donut": 61,
        "donutColor": "hsl(123, 70%, 50%)",
        "junk": 13,
        "junkColor": "hsl(216, 70%, 50%)",
        "sushi": 15,
        "sushiColor": "hsl(105, 70%, 50%)",
        "ramen": 97,
        "ramenColor": "hsl(165, 70%, 50%)",
        "curry": 19,
        "curryColor": "hsl(178, 70%, 50%)",
        "udon": 36,
        "udonColor": "hsl(284, 70%, 50%)",
        "bagel": 6,
        "bagelColor": "hsl(221, 70%, 50%)",
        "yakitori": 67,
        "yakitoriColor": "hsl(350, 70%, 50%)",
        "takoyaki": 37,
        "takoyakiColor": "hsl(267, 70%, 50%)",
        "tacos": 64,
        "tacosColor": "hsl(339, 70%, 50%)",
        "miso soup": 33,
        "miso soupColor": "hsl(174, 70%, 50%)",
        "tortilla": 38,
        "tortillaColor": "hsl(121, 70%, 50%)",
        "tapas": 93,
        "tapasColor": "hsl(259, 70%, 50%)",
        "chipirones": 8,
        "chipironesColor": "hsl(121, 70%, 50%)",
        "gazpacho": 65,
        "gazpachoColor": "hsl(145, 70%, 50%)",
        "soba": 81,
        "sobaColor": "hsl(47, 70%, 50%)",
        "bavette": 91,
        "bavetteColor": "hsl(245, 70%, 50%)",
        "steak": 66,
        "steakColor": "hsl(337, 70%, 50%)",
        "pizza": 30,
        "pizzaColor": "hsl(185, 70%, 50%)",
        "spaghetti": 1,
        "spaghettiColor": "hsl(31, 70%, 50%)",
        "ravioli": 93,
        "ravioliColor": "hsl(81, 70%, 50%)",
        "salad": 7,
        "saladColor": "hsl(166, 70%, 50%)",
        "pad thai": 79,
        "pad thaiColor": "hsl(178, 70%, 50%)",
        "bun": 15,
        "bunColor": "hsl(243, 70%, 50%)",
        "waffle": 56,
        "waffleColor": "hsl(16, 70%, 50%)",
        "crepe": 12,
        "crepeColor": "hsl(44, 70%, 50%)",
        "churros": 94,
        "churrosColor": "hsl(253, 70%, 50%)",
        "paella": 99,
        "paellaColor": "hsl(326, 70%, 50%)",
        "empanadas": 31,
        "empanadasColor": "hsl(24, 70%, 50%)",
        "bruschetta": 8,
        "bruschettaColor": "hsl(160, 70%, 50%)",
        "onion soup": 96,
        "onion soupColor": "hsl(69, 70%, 50%)",
        "cassoulet": 29,
        "cassouletColor": "hsl(162, 70%, 50%)",
        "bouillabaisse": 0,
        "bouillabaisseColor": "hsl(306, 70%, 50%)",
        "unagi": 91,
        "unagiColor": "hsl(263, 70%, 50%)",
        "tempura": 91,
        "tempuraColor": "hsl(70, 70%, 50%)",
        "tonkatsu": 5,
        "tonkatsuColor": "hsl(176, 70%, 50%)",
        "shabu-shabu": 57,
        "shabu-shabuColor": "hsl(93, 70%, 50%)",
        "twinkies": 23,
        "twinkiesColor": "hsl(78, 70%, 50%)",
        "jerky": 66,
        "jerkyColor": "hsl(84, 70%, 50%)",
        "fajitas": 80,
        "fajitasColor": "hsl(3, 70%, 50%)",
        "jambalaya": 10,
        "jambalayaColor": "hsl(40, 70%, 50%)",
        "meatloaf": 41,
        "meatloafColor": "hsl(25, 70%, 50%)",
        "mac n' cheese": 87,
        "mac n' cheeseColor": "hsl(135, 70%, 50%)",
        "baked beans": 78,
        "baked beansColor": "hsl(231, 70%, 50%)",
        "popcorn": 86,
        "popcornColor": "hsl(146, 70%, 50%)",
        "buffalo wings": 89,
        "buffalo wingsColor": "hsl(107, 70%, 50%)",
        "BBQ ribs": 48,
        "BBQ ribsColor": "hsl(267, 70%, 50%)",
        "apple pie": 7,
        "apple pieColor": "hsl(173, 70%, 50%)",
        "nachos": 92,
        "nachosColor": "hsl(38, 70%, 50%)",
        "risotto": 4,
        "risottoColor": "hsl(40, 70%, 50%)",
        "tiramisu": 6,
        "tiramisuColor": "hsl(340, 70%, 50%)"
    },
    {
        "country": "AT",
        "hot dog": 77,
        "hot dogColor": "hsl(49, 70%, 50%)",
        "burger": 95,
        "burgerColor": "hsl(204, 70%, 50%)",
        "sandwich": 71,
        "sandwichColor": "hsl(155, 70%, 50%)",
        "kebab": 58,
        "kebabColor": "hsl(191, 70%, 50%)",
        "fries": 39,
        "friesColor": "hsl(257, 70%, 50%)",
        "donut": 12,
        "donutColor": "hsl(263, 70%, 50%)",
        "junk": 67,
        "junkColor": "hsl(91, 70%, 50%)",
        "sushi": 39,
        "sushiColor": "hsl(283, 70%, 50%)",
        "ramen": 16,
        "ramenColor": "hsl(145, 70%, 50%)",
        "curry": 71,
        "curryColor": "hsl(85, 70%, 50%)",
        "udon": 60,
        "udonColor": "hsl(116, 70%, 50%)",
        "bagel": 76,
        "bagelColor": "hsl(137, 70%, 50%)",
        "yakitori": 36,
        "yakitoriColor": "hsl(106, 70%, 50%)",
        "takoyaki": 60,
        "takoyakiColor": "hsl(81, 70%, 50%)",
        "tacos": 43,
        "tacosColor": "hsl(76, 70%, 50%)",
        "miso soup": 41,
        "miso soupColor": "hsl(90, 70%, 50%)",
        "tortilla": 7,
        "tortillaColor": "hsl(203, 70%, 50%)",
        "tapas": 99,
        "tapasColor": "hsl(185, 70%, 50%)",
        "chipirones": 5,
        "chipironesColor": "hsl(223, 70%, 50%)",
        "gazpacho": 53,
        "gazpachoColor": "hsl(260, 70%, 50%)",
        "soba": 86,
        "sobaColor": "hsl(243, 70%, 50%)",
        "bavette": 6,
        "bavetteColor": "hsl(91, 70%, 50%)",
        "steak": 43,
        "steakColor": "hsl(280, 70%, 50%)",
        "pizza": 12,
        "pizzaColor": "hsl(287, 70%, 50%)",
        "spaghetti": 100,
        "spaghettiColor": "hsl(197, 70%, 50%)",
        "ravioli": 70,
        "ravioliColor": "hsl(310, 70%, 50%)",
        "salad": 74,
        "saladColor": "hsl(151, 70%, 50%)",
        "pad thai": 19,
        "pad thaiColor": "hsl(152, 70%, 50%)",
        "bun": 39,
        "bunColor": "hsl(94, 70%, 50%)",
        "waffle": 96,
        "waffleColor": "hsl(65, 70%, 50%)",
        "crepe": 95,
        "crepeColor": "hsl(304, 70%, 50%)",
        "churros": 91,
        "churrosColor": "hsl(172, 70%, 50%)",
        "paella": 64,
        "paellaColor": "hsl(335, 70%, 50%)",
        "empanadas": 24,
        "empanadasColor": "hsl(323, 70%, 50%)",
        "bruschetta": 99,
        "bruschettaColor": "hsl(196, 70%, 50%)",
        "onion soup": 44,
        "onion soupColor": "hsl(238, 70%, 50%)",
        "cassoulet": 88,
        "cassouletColor": "hsl(40, 70%, 50%)",
        "bouillabaisse": 8,
        "bouillabaisseColor": "hsl(326, 70%, 50%)",
        "unagi": 10,
        "unagiColor": "hsl(177, 70%, 50%)",
        "tempura": 75,
        "tempuraColor": "hsl(202, 70%, 50%)",
        "tonkatsu": 84,
        "tonkatsuColor": "hsl(158, 70%, 50%)",
        "shabu-shabu": 6,
        "shabu-shabuColor": "hsl(10, 70%, 50%)",
        "twinkies": 81,
        "twinkiesColor": "hsl(31, 70%, 50%)",
        "jerky": 29,
        "jerkyColor": "hsl(40, 70%, 50%)",
        "fajitas": 78,
        "fajitasColor": "hsl(105, 70%, 50%)",
        "jambalaya": 57,
        "jambalayaColor": "hsl(139, 70%, 50%)",
        "meatloaf": 63,
        "meatloafColor": "hsl(54, 70%, 50%)",
        "mac n' cheese": 72,
        "mac n' cheeseColor": "hsl(260, 70%, 50%)",
        "baked beans": 91,
        "baked beansColor": "hsl(146, 70%, 50%)",
        "popcorn": 64,
        "popcornColor": "hsl(348, 70%, 50%)",
        "buffalo wings": 50,
        "buffalo wingsColor": "hsl(101, 70%, 50%)",
        "BBQ ribs": 5,
        "BBQ ribsColor": "hsl(5, 70%, 50%)",
        "apple pie": 20,
        "apple pieColor": "hsl(155, 70%, 50%)",
        "nachos": 92,
        "nachosColor": "hsl(141, 70%, 50%)",
        "risotto": 33,
        "risottoColor": "hsl(211, 70%, 50%)",
        "tiramisu": 5,
        "tiramisuColor": "hsl(311, 70%, 50%)"
    },
    {
        "country": "AU",
        "hot dog": 27,
        "hot dogColor": "hsl(205, 70%, 50%)",
        "burger": 52,
        "burgerColor": "hsl(89, 70%, 50%)",
        "sandwich": 98,
        "sandwichColor": "hsl(293, 70%, 50%)",
        "kebab": 54,
        "kebabColor": "hsl(211, 70%, 50%)",
        "fries": 31,
        "friesColor": "hsl(256, 70%, 50%)",
        "donut": 82,
        "donutColor": "hsl(47, 70%, 50%)",
        "junk": 36,
        "junkColor": "hsl(42, 70%, 50%)",
        "sushi": 49,
        "sushiColor": "hsl(159, 70%, 50%)",
        "ramen": 94,
        "ramenColor": "hsl(161, 70%, 50%)",
        "curry": 6,
        "curryColor": "hsl(129, 70%, 50%)",
        "udon": 97,
        "udonColor": "hsl(263, 70%, 50%)",
        "bagel": 54,
        "bagelColor": "hsl(125, 70%, 50%)",
        "yakitori": 62,
        "yakitoriColor": "hsl(117, 70%, 50%)",
        "takoyaki": 99,
        "takoyakiColor": "hsl(296, 70%, 50%)",
        "tacos": 42,
        "tacosColor": "hsl(207, 70%, 50%)",
        "miso soup": 25,
        "miso soupColor": "hsl(353, 70%, 50%)",
        "tortilla": 19,
        "tortillaColor": "hsl(29, 70%, 50%)",
        "tapas": 93,
        "tapasColor": "hsl(129, 70%, 50%)",
        "chipirones": 60,
        "chipironesColor": "hsl(115, 70%, 50%)",
        "gazpacho": 96,
        "gazpachoColor": "hsl(182, 70%, 50%)",
        "soba": 23,
        "sobaColor": "hsl(118, 70%, 50%)",
        "bavette": 6,
        "bavetteColor": "hsl(30, 70%, 50%)",
        "steak": 20,
        "steakColor": "hsl(21, 70%, 50%)",
        "pizza": 34,
        "pizzaColor": "hsl(128, 70%, 50%)",
        "spaghetti": 39,
        "spaghettiColor": "hsl(50, 70%, 50%)",
        "ravioli": 99,
        "ravioliColor": "hsl(52, 70%, 50%)",
        "salad": 21,
        "saladColor": "hsl(268, 70%, 50%)",
        "pad thai": 13,
        "pad thaiColor": "hsl(102, 70%, 50%)",
        "bun": 98,
        "bunColor": "hsl(52, 70%, 50%)",
        "waffle": 99,
        "waffleColor": "hsl(111, 70%, 50%)",
        "crepe": 39,
        "crepeColor": "hsl(181, 70%, 50%)",
        "churros": 9,
        "churrosColor": "hsl(310, 70%, 50%)",
        "paella": 66,
        "paellaColor": "hsl(241, 70%, 50%)",
        "empanadas": 85,
        "empanadasColor": "hsl(55, 70%, 50%)",
        "bruschetta": 46,
        "bruschettaColor": "hsl(215, 70%, 50%)",
        "onion soup": 35,
        "onion soupColor": "hsl(90, 70%, 50%)",
        "cassoulet": 41,
        "cassouletColor": "hsl(356, 70%, 50%)",
        "bouillabaisse": 96,
        "bouillabaisseColor": "hsl(73, 70%, 50%)",
        "unagi": 100,
        "unagiColor": "hsl(170, 70%, 50%)",
        "tempura": 81,
        "tempuraColor": "hsl(225, 70%, 50%)",
        "tonkatsu": 78,
        "tonkatsuColor": "hsl(184, 70%, 50%)",
        "shabu-shabu": 77,
        "shabu-shabuColor": "hsl(236, 70%, 50%)",
        "twinkies": 53,
        "twinkiesColor": "hsl(42, 70%, 50%)",
        "jerky": 97,
        "jerkyColor": "hsl(252, 70%, 50%)",
        "fajitas": 48,
        "fajitasColor": "hsl(171, 70%, 50%)",
        "jambalaya": 100,
        "jambalayaColor": "hsl(201, 70%, 50%)",
        "meatloaf": 36,
        "meatloafColor": "hsl(146, 70%, 50%)",
        "mac n' cheese": 18,
        "mac n' cheeseColor": "hsl(30, 70%, 50%)",
        "baked beans": 78,
        "baked beansColor": "hsl(139, 70%, 50%)",
        "popcorn": 11,
        "popcornColor": "hsl(259, 70%, 50%)",
        "buffalo wings": 3,
        "buffalo wingsColor": "hsl(314, 70%, 50%)",
        "BBQ ribs": 62,
        "BBQ ribsColor": "hsl(175, 70%, 50%)",
        "apple pie": 22,
        "apple pieColor": "hsl(52, 70%, 50%)",
        "nachos": 91,
        "nachosColor": "hsl(322, 70%, 50%)",
        "risotto": 34,
        "risottoColor": "hsl(42, 70%, 50%)",
        "tiramisu": 74,
        "tiramisuColor": "hsl(20, 70%, 50%)"
    },
    {
        "country": "AW",
        "hot dog": 49,
        "hot dogColor": "hsl(200, 70%, 50%)",
        "burger": 75,
        "burgerColor": "hsl(232, 70%, 50%)",
        "sandwich": 64,
        "sandwichColor": "hsl(78, 70%, 50%)",
        "kebab": 89,
        "kebabColor": "hsl(255, 70%, 50%)",
        "fries": 27,
        "friesColor": "hsl(241, 70%, 50%)",
        "donut": 31,
        "donutColor": "hsl(215, 70%, 50%)",
        "junk": 9,
        "junkColor": "hsl(193, 70%, 50%)",
        "sushi": 23,
        "sushiColor": "hsl(66, 70%, 50%)",
        "ramen": 37,
        "ramenColor": "hsl(37, 70%, 50%)",
        "curry": 39,
        "curryColor": "hsl(76, 70%, 50%)",
        "udon": 79,
        "udonColor": "hsl(118, 70%, 50%)",
        "bagel": 20,
        "bagelColor": "hsl(343, 70%, 50%)",
        "yakitori": 68,
        "yakitoriColor": "hsl(106, 70%, 50%)",
        "takoyaki": 19,
        "takoyakiColor": "hsl(198, 70%, 50%)",
        "tacos": 27,
        "tacosColor": "hsl(60, 70%, 50%)",
        "miso soup": 94,
        "miso soupColor": "hsl(353, 70%, 50%)",
        "tortilla": 71,
        "tortillaColor": "hsl(236, 70%, 50%)",
        "tapas": 60,
        "tapasColor": "hsl(162, 70%, 50%)",
        "chipirones": 46,
        "chipironesColor": "hsl(41, 70%, 50%)",
        "gazpacho": 80,
        "gazpachoColor": "hsl(239, 70%, 50%)",
        "soba": 60,
        "sobaColor": "hsl(261, 70%, 50%)",
        "bavette": 24,
        "bavetteColor": "hsl(110, 70%, 50%)",
        "steak": 59,
        "steakColor": "hsl(204, 70%, 50%)",
        "pizza": 28,
        "pizzaColor": "hsl(194, 70%, 50%)",
        "spaghetti": 28,
        "spaghettiColor": "hsl(244, 70%, 50%)",
        "ravioli": 41,
        "ravioliColor": "hsl(250, 70%, 50%)",
        "salad": 30,
        "saladColor": "hsl(77, 70%, 50%)",
        "pad thai": 25,
        "pad thaiColor": "hsl(315, 70%, 50%)",
        "bun": 40,
        "bunColor": "hsl(182, 70%, 50%)",
        "waffle": 45,
        "waffleColor": "hsl(47, 70%, 50%)",
        "crepe": 40,
        "crepeColor": "hsl(51, 70%, 50%)",
        "churros": 80,
        "churrosColor": "hsl(58, 70%, 50%)",
        "paella": 97,
        "paellaColor": "hsl(116, 70%, 50%)",
        "empanadas": 44,
        "empanadasColor": "hsl(343, 70%, 50%)",
        "bruschetta": 67,
        "bruschettaColor": "hsl(180, 70%, 50%)",
        "onion soup": 26,
        "onion soupColor": "hsl(216, 70%, 50%)",
        "cassoulet": 83,
        "cassouletColor": "hsl(343, 70%, 50%)",
        "bouillabaisse": 15,
        "bouillabaisseColor": "hsl(112, 70%, 50%)",
        "unagi": 68,
        "unagiColor": "hsl(204, 70%, 50%)",
        "tempura": 81,
        "tempuraColor": "hsl(250, 70%, 50%)",
        "tonkatsu": 17,
        "tonkatsuColor": "hsl(31, 70%, 50%)",
        "shabu-shabu": 23,
        "shabu-shabuColor": "hsl(67, 70%, 50%)",
        "twinkies": 43,
        "twinkiesColor": "hsl(254, 70%, 50%)",
        "jerky": 55,
        "jerkyColor": "hsl(205, 70%, 50%)",
        "fajitas": 39,
        "fajitasColor": "hsl(139, 70%, 50%)",
        "jambalaya": 91,
        "jambalayaColor": "hsl(295, 70%, 50%)",
        "meatloaf": 24,
        "meatloafColor": "hsl(153, 70%, 50%)",
        "mac n' cheese": 7,
        "mac n' cheeseColor": "hsl(80, 70%, 50%)",
        "baked beans": 92,
        "baked beansColor": "hsl(194, 70%, 50%)",
        "popcorn": 33,
        "popcornColor": "hsl(256, 70%, 50%)",
        "buffalo wings": 17,
        "buffalo wingsColor": "hsl(324, 70%, 50%)",
        "BBQ ribs": 32,
        "BBQ ribsColor": "hsl(150, 70%, 50%)",
        "apple pie": 18,
        "apple pieColor": "hsl(239, 70%, 50%)",
        "nachos": 69,
        "nachosColor": "hsl(90, 70%, 50%)",
        "risotto": 7,
        "risottoColor": "hsl(232, 70%, 50%)",
        "tiramisu": 28,
        "tiramisuColor": "hsl(277, 70%, 50%)"
    },
    {
        "country": "AX",
        "hot dog": 73,
        "hot dogColor": "hsl(209, 70%, 50%)",
        "burger": 61,
        "burgerColor": "hsl(281, 70%, 50%)",
        "sandwich": 44,
        "sandwichColor": "hsl(283, 70%, 50%)",
        "kebab": 74,
        "kebabColor": "hsl(23, 70%, 50%)",
        "fries": 56,
        "friesColor": "hsl(327, 70%, 50%)",
        "donut": 15,
        "donutColor": "hsl(159, 70%, 50%)",
        "junk": 59,
        "junkColor": "hsl(35, 70%, 50%)",
        "sushi": 26,
        "sushiColor": "hsl(250, 70%, 50%)",
        "ramen": 83,
        "ramenColor": "hsl(264, 70%, 50%)",
        "curry": 52,
        "curryColor": "hsl(358, 70%, 50%)",
        "udon": 83,
        "udonColor": "hsl(287, 70%, 50%)",
        "bagel": 34,
        "bagelColor": "hsl(261, 70%, 50%)",
        "yakitori": 37,
        "yakitoriColor": "hsl(246, 70%, 50%)",
        "takoyaki": 55,
        "takoyakiColor": "hsl(52, 70%, 50%)",
        "tacos": 13,
        "tacosColor": "hsl(277, 70%, 50%)",
        "miso soup": 7,
        "miso soupColor": "hsl(11, 70%, 50%)",
        "tortilla": 52,
        "tortillaColor": "hsl(106, 70%, 50%)",
        "tapas": 82,
        "tapasColor": "hsl(263, 70%, 50%)",
        "chipirones": 19,
        "chipironesColor": "hsl(262, 70%, 50%)",
        "gazpacho": 62,
        "gazpachoColor": "hsl(312, 70%, 50%)",
        "soba": 30,
        "sobaColor": "hsl(141, 70%, 50%)",
        "bavette": 24,
        "bavetteColor": "hsl(66, 70%, 50%)",
        "steak": 87,
        "steakColor": "hsl(218, 70%, 50%)",
        "pizza": 29,
        "pizzaColor": "hsl(74, 70%, 50%)",
        "spaghetti": 36,
        "spaghettiColor": "hsl(227, 70%, 50%)",
        "ravioli": 61,
        "ravioliColor": "hsl(159, 70%, 50%)",
        "salad": 5,
        "saladColor": "hsl(193, 70%, 50%)",
        "pad thai": 82,
        "pad thaiColor": "hsl(247, 70%, 50%)",
        "bun": 98,
        "bunColor": "hsl(208, 70%, 50%)",
        "waffle": 10,
        "waffleColor": "hsl(51, 70%, 50%)",
        "crepe": 23,
        "crepeColor": "hsl(159, 70%, 50%)",
        "churros": 97,
        "churrosColor": "hsl(110, 70%, 50%)",
        "paella": 42,
        "paellaColor": "hsl(347, 70%, 50%)",
        "empanadas": 44,
        "empanadasColor": "hsl(17, 70%, 50%)",
        "bruschetta": 85,
        "bruschettaColor": "hsl(291, 70%, 50%)",
        "onion soup": 70,
        "onion soupColor": "hsl(112, 70%, 50%)",
        "cassoulet": 38,
        "cassouletColor": "hsl(92, 70%, 50%)",
        "bouillabaisse": 97,
        "bouillabaisseColor": "hsl(313, 70%, 50%)",
        "unagi": 2,
        "unagiColor": "hsl(273, 70%, 50%)",
        "tempura": 91,
        "tempuraColor": "hsl(173, 70%, 50%)",
        "tonkatsu": 76,
        "tonkatsuColor": "hsl(339, 70%, 50%)",
        "shabu-shabu": 25,
        "shabu-shabuColor": "hsl(321, 70%, 50%)",
        "twinkies": 41,
        "twinkiesColor": "hsl(186, 70%, 50%)",
        "jerky": 18,
        "jerkyColor": "hsl(327, 70%, 50%)",
        "fajitas": 48,
        "fajitasColor": "hsl(116, 70%, 50%)",
        "jambalaya": 59,
        "jambalayaColor": "hsl(120, 70%, 50%)",
        "meatloaf": 47,
        "meatloafColor": "hsl(310, 70%, 50%)",
        "mac n' cheese": 7,
        "mac n' cheeseColor": "hsl(205, 70%, 50%)",
        "baked beans": 58,
        "baked beansColor": "hsl(219, 70%, 50%)",
        "popcorn": 26,
        "popcornColor": "hsl(45, 70%, 50%)",
        "buffalo wings": 43,
        "buffalo wingsColor": "hsl(70, 70%, 50%)",
        "BBQ ribs": 69,
        "BBQ ribsColor": "hsl(144, 70%, 50%)",
        "apple pie": 84,
        "apple pieColor": "hsl(133, 70%, 50%)",
        "nachos": 63,
        "nachosColor": "hsl(294, 70%, 50%)",
        "risotto": 23,
        "risottoColor": "hsl(254, 70%, 50%)",
        "tiramisu": 87,
        "tiramisuColor": "hsl(286, 70%, 50%)"
    },
    {
        "country": "AZ",
        "hot dog": 91,
        "hot dogColor": "hsl(120, 70%, 50%)",
        "burger": 78,
        "burgerColor": "hsl(211, 70%, 50%)",
        "sandwich": 93,
        "sandwichColor": "hsl(25, 70%, 50%)",
        "kebab": 4,
        "kebabColor": "hsl(239, 70%, 50%)",
        "fries": 71,
        "friesColor": "hsl(329, 70%, 50%)",
        "donut": 1,
        "donutColor": "hsl(329, 70%, 50%)",
        "junk": 39,
        "junkColor": "hsl(356, 70%, 50%)",
        "sushi": 23,
        "sushiColor": "hsl(276, 70%, 50%)",
        "ramen": 63,
        "ramenColor": "hsl(243, 70%, 50%)",
        "curry": 66,
        "curryColor": "hsl(238, 70%, 50%)",
        "udon": 28,
        "udonColor": "hsl(133, 70%, 50%)",
        "bagel": 7,
        "bagelColor": "hsl(95, 70%, 50%)",
        "yakitori": 84,
        "yakitoriColor": "hsl(161, 70%, 50%)",
        "takoyaki": 70,
        "takoyakiColor": "hsl(238, 70%, 50%)",
        "tacos": 24,
        "tacosColor": "hsl(202, 70%, 50%)",
        "miso soup": 13,
        "miso soupColor": "hsl(261, 70%, 50%)",
        "tortilla": 23,
        "tortillaColor": "hsl(42, 70%, 50%)",
        "tapas": 14,
        "tapasColor": "hsl(93, 70%, 50%)",
        "chipirones": 96,
        "chipironesColor": "hsl(82, 70%, 50%)",
        "gazpacho": 28,
        "gazpachoColor": "hsl(348, 70%, 50%)",
        "soba": 46,
        "sobaColor": "hsl(242, 70%, 50%)",
        "bavette": 88,
        "bavetteColor": "hsl(198, 70%, 50%)",
        "steak": 15,
        "steakColor": "hsl(315, 70%, 50%)",
        "pizza": 28,
        "pizzaColor": "hsl(105, 70%, 50%)",
        "spaghetti": 83,
        "spaghettiColor": "hsl(266, 70%, 50%)",
        "ravioli": 59,
        "ravioliColor": "hsl(71, 70%, 50%)",
        "salad": 95,
        "saladColor": "hsl(17, 70%, 50%)",
        "pad thai": 38,
        "pad thaiColor": "hsl(184, 70%, 50%)",
        "bun": 4,
        "bunColor": "hsl(105, 70%, 50%)",
        "waffle": 52,
        "waffleColor": "hsl(238, 70%, 50%)",
        "crepe": 41,
        "crepeColor": "hsl(332, 70%, 50%)",
        "churros": 21,
        "churrosColor": "hsl(307, 70%, 50%)",
        "paella": 19,
        "paellaColor": "hsl(344, 70%, 50%)",
        "empanadas": 21,
        "empanadasColor": "hsl(147, 70%, 50%)",
        "bruschetta": 73,
        "bruschettaColor": "hsl(201, 70%, 50%)",
        "onion soup": 52,
        "onion soupColor": "hsl(26, 70%, 50%)",
        "cassoulet": 92,
        "cassouletColor": "hsl(223, 70%, 50%)",
        "bouillabaisse": 33,
        "bouillabaisseColor": "hsl(203, 70%, 50%)",
        "unagi": 34,
        "unagiColor": "hsl(250, 70%, 50%)",
        "tempura": 42,
        "tempuraColor": "hsl(343, 70%, 50%)",
        "tonkatsu": 4,
        "tonkatsuColor": "hsl(336, 70%, 50%)",
        "shabu-shabu": 53,
        "shabu-shabuColor": "hsl(15, 70%, 50%)",
        "twinkies": 76,
        "twinkiesColor": "hsl(154, 70%, 50%)",
        "jerky": 61,
        "jerkyColor": "hsl(85, 70%, 50%)",
        "fajitas": 79,
        "fajitasColor": "hsl(291, 70%, 50%)",
        "jambalaya": 83,
        "jambalayaColor": "hsl(144, 70%, 50%)",
        "meatloaf": 31,
        "meatloafColor": "hsl(304, 70%, 50%)",
        "mac n' cheese": 37,
        "mac n' cheeseColor": "hsl(60, 70%, 50%)",
        "baked beans": 40,
        "baked beansColor": "hsl(107, 70%, 50%)",
        "popcorn": 45,
        "popcornColor": "hsl(318, 70%, 50%)",
        "buffalo wings": 66,
        "buffalo wingsColor": "hsl(76, 70%, 50%)",
        "BBQ ribs": 49,
        "BBQ ribsColor": "hsl(20, 70%, 50%)",
        "apple pie": 22,
        "apple pieColor": "hsl(96, 70%, 50%)",
        "nachos": 82,
        "nachosColor": "hsl(113, 70%, 50%)",
        "risotto": 29,
        "risottoColor": "hsl(348, 70%, 50%)",
        "tiramisu": 8,
        "tiramisuColor": "hsl(316, 70%, 50%)"
    },
    {
        "country": "BA",
        "hot dog": 63,
        "hot dogColor": "hsl(331, 70%, 50%)",
        "burger": 71,
        "burgerColor": "hsl(284, 70%, 50%)",
        "sandwich": 63,
        "sandwichColor": "hsl(181, 70%, 50%)",
        "kebab": 100,
        "kebabColor": "hsl(234, 70%, 50%)",
        "fries": 36,
        "friesColor": "hsl(341, 70%, 50%)",
        "donut": 56,
        "donutColor": "hsl(250, 70%, 50%)",
        "junk": 82,
        "junkColor": "hsl(27, 70%, 50%)",
        "sushi": 52,
        "sushiColor": "hsl(174, 70%, 50%)",
        "ramen": 49,
        "ramenColor": "hsl(153, 70%, 50%)",
        "curry": 24,
        "curryColor": "hsl(187, 70%, 50%)",
        "udon": 42,
        "udonColor": "hsl(200, 70%, 50%)",
        "bagel": 44,
        "bagelColor": "hsl(263, 70%, 50%)",
        "yakitori": 47,
        "yakitoriColor": "hsl(29, 70%, 50%)",
        "takoyaki": 17,
        "takoyakiColor": "hsl(204, 70%, 50%)",
        "tacos": 75,
        "tacosColor": "hsl(95, 70%, 50%)",
        "miso soup": 91,
        "miso soupColor": "hsl(220, 70%, 50%)",
        "tortilla": 90,
        "tortillaColor": "hsl(171, 70%, 50%)",
        "tapas": 71,
        "tapasColor": "hsl(7, 70%, 50%)",
        "chipirones": 78,
        "chipironesColor": "hsl(171, 70%, 50%)",
        "gazpacho": 27,
        "gazpachoColor": "hsl(297, 70%, 50%)",
        "soba": 30,
        "sobaColor": "hsl(197, 70%, 50%)",
        "bavette": 35,
        "bavetteColor": "hsl(138, 70%, 50%)",
        "steak": 81,
        "steakColor": "hsl(168, 70%, 50%)",
        "pizza": 44,
        "pizzaColor": "hsl(326, 70%, 50%)",
        "spaghetti": 47,
        "spaghettiColor": "hsl(218, 70%, 50%)",
        "ravioli": 59,
        "ravioliColor": "hsl(209, 70%, 50%)",
        "salad": 96,
        "saladColor": "hsl(74, 70%, 50%)",
        "pad thai": 19,
        "pad thaiColor": "hsl(250, 70%, 50%)",
        "bun": 73,
        "bunColor": "hsl(338, 70%, 50%)",
        "waffle": 32,
        "waffleColor": "hsl(155, 70%, 50%)",
        "crepe": 7,
        "crepeColor": "hsl(168, 70%, 50%)",
        "churros": 24,
        "churrosColor": "hsl(55, 70%, 50%)",
        "paella": 70,
        "paellaColor": "hsl(76, 70%, 50%)",
        "empanadas": 30,
        "empanadasColor": "hsl(287, 70%, 50%)",
        "bruschetta": 76,
        "bruschettaColor": "hsl(346, 70%, 50%)",
        "onion soup": 16,
        "onion soupColor": "hsl(50, 70%, 50%)",
        "cassoulet": 57,
        "cassouletColor": "hsl(272, 70%, 50%)",
        "bouillabaisse": 33,
        "bouillabaisseColor": "hsl(67, 70%, 50%)",
        "unagi": 28,
        "unagiColor": "hsl(101, 70%, 50%)",
        "tempura": 94,
        "tempuraColor": "hsl(166, 70%, 50%)",
        "tonkatsu": 3,
        "tonkatsuColor": "hsl(142, 70%, 50%)",
        "shabu-shabu": 85,
        "shabu-shabuColor": "hsl(335, 70%, 50%)",
        "twinkies": 40,
        "twinkiesColor": "hsl(57, 70%, 50%)",
        "jerky": 59,
        "jerkyColor": "hsl(111, 70%, 50%)",
        "fajitas": 40,
        "fajitasColor": "hsl(224, 70%, 50%)",
        "jambalaya": 84,
        "jambalayaColor": "hsl(156, 70%, 50%)",
        "meatloaf": 79,
        "meatloafColor": "hsl(326, 70%, 50%)",
        "mac n' cheese": 39,
        "mac n' cheeseColor": "hsl(359, 70%, 50%)",
        "baked beans": 63,
        "baked beansColor": "hsl(330, 70%, 50%)",
        "popcorn": 63,
        "popcornColor": "hsl(181, 70%, 50%)",
        "buffalo wings": 54,
        "buffalo wingsColor": "hsl(64, 70%, 50%)",
        "BBQ ribs": 41,
        "BBQ ribsColor": "hsl(119, 70%, 50%)",
        "apple pie": 15,
        "apple pieColor": "hsl(257, 70%, 50%)",
        "nachos": 47,
        "nachosColor": "hsl(216, 70%, 50%)",
        "risotto": 88,
        "risottoColor": "hsl(252, 70%, 50%)",
        "tiramisu": 27,
        "tiramisuColor": "hsl(168, 70%, 50%)"
    },
    {
        "country": "BB",
        "hot dog": 76,
        "hot dogColor": "hsl(319, 70%, 50%)",
        "burger": 12,
        "burgerColor": "hsl(32, 70%, 50%)",
        "sandwich": 76,
        "sandwichColor": "hsl(295, 70%, 50%)",
        "kebab": 20,
        "kebabColor": "hsl(336, 70%, 50%)",
        "fries": 75,
        "friesColor": "hsl(306, 70%, 50%)",
        "donut": 58,
        "donutColor": "hsl(176, 70%, 50%)",
        "junk": 96,
        "junkColor": "hsl(43, 70%, 50%)",
        "sushi": 65,
        "sushiColor": "hsl(147, 70%, 50%)",
        "ramen": 63,
        "ramenColor": "hsl(42, 70%, 50%)",
        "curry": 61,
        "curryColor": "hsl(291, 70%, 50%)",
        "udon": 7,
        "udonColor": "hsl(192, 70%, 50%)",
        "bagel": 23,
        "bagelColor": "hsl(66, 70%, 50%)",
        "yakitori": 11,
        "yakitoriColor": "hsl(309, 70%, 50%)",
        "takoyaki": 68,
        "takoyakiColor": "hsl(70, 70%, 50%)",
        "tacos": 44,
        "tacosColor": "hsl(183, 70%, 50%)",
        "miso soup": 18,
        "miso soupColor": "hsl(271, 70%, 50%)",
        "tortilla": 25,
        "tortillaColor": "hsl(47, 70%, 50%)",
        "tapas": 43,
        "tapasColor": "hsl(124, 70%, 50%)",
        "chipirones": 20,
        "chipironesColor": "hsl(237, 70%, 50%)",
        "gazpacho": 45,
        "gazpachoColor": "hsl(13, 70%, 50%)",
        "soba": 57,
        "sobaColor": "hsl(73, 70%, 50%)",
        "bavette": 80,
        "bavetteColor": "hsl(150, 70%, 50%)",
        "steak": 22,
        "steakColor": "hsl(124, 70%, 50%)",
        "pizza": 21,
        "pizzaColor": "hsl(90, 70%, 50%)",
        "spaghetti": 66,
        "spaghettiColor": "hsl(133, 70%, 50%)",
        "ravioli": 10,
        "ravioliColor": "hsl(205, 70%, 50%)",
        "salad": 14,
        "saladColor": "hsl(305, 70%, 50%)",
        "pad thai": 49,
        "pad thaiColor": "hsl(230, 70%, 50%)",
        "bun": 22,
        "bunColor": "hsl(357, 70%, 50%)",
        "waffle": 20,
        "waffleColor": "hsl(92, 70%, 50%)",
        "crepe": 28,
        "crepeColor": "hsl(8, 70%, 50%)",
        "churros": 34,
        "churrosColor": "hsl(229, 70%, 50%)",
        "paella": 96,
        "paellaColor": "hsl(178, 70%, 50%)",
        "empanadas": 1,
        "empanadasColor": "hsl(67, 70%, 50%)",
        "bruschetta": 67,
        "bruschettaColor": "hsl(295, 70%, 50%)",
        "onion soup": 72,
        "onion soupColor": "hsl(110, 70%, 50%)",
        "cassoulet": 30,
        "cassouletColor": "hsl(3, 70%, 50%)",
        "bouillabaisse": 95,
        "bouillabaisseColor": "hsl(236, 70%, 50%)",
        "unagi": 1,
        "unagiColor": "hsl(36, 70%, 50%)",
        "tempura": 55,
        "tempuraColor": "hsl(112, 70%, 50%)",
        "tonkatsu": 32,
        "tonkatsuColor": "hsl(91, 70%, 50%)",
        "shabu-shabu": 21,
        "shabu-shabuColor": "hsl(357, 70%, 50%)",
        "twinkies": 53,
        "twinkiesColor": "hsl(45, 70%, 50%)",
        "jerky": 85,
        "jerkyColor": "hsl(247, 70%, 50%)",
        "fajitas": 16,
        "fajitasColor": "hsl(45, 70%, 50%)",
        "jambalaya": 11,
        "jambalayaColor": "hsl(341, 70%, 50%)",
        "meatloaf": 3,
        "meatloafColor": "hsl(81, 70%, 50%)",
        "mac n' cheese": 7,
        "mac n' cheeseColor": "hsl(231, 70%, 50%)",
        "baked beans": 98,
        "baked beansColor": "hsl(131, 70%, 50%)",
        "popcorn": 22,
        "popcornColor": "hsl(344, 70%, 50%)",
        "buffalo wings": 91,
        "buffalo wingsColor": "hsl(145, 70%, 50%)",
        "BBQ ribs": 14,
        "BBQ ribsColor": "hsl(237, 70%, 50%)",
        "apple pie": 28,
        "apple pieColor": "hsl(81, 70%, 50%)",
        "nachos": 66,
        "nachosColor": "hsl(156, 70%, 50%)",
        "risotto": 40,
        "risottoColor": "hsl(78, 70%, 50%)",
        "tiramisu": 92,
        "tiramisuColor": "hsl(10, 70%, 50%)"
    },
    {
        "country": "BD",
        "hot dog": 66,
        "hot dogColor": "hsl(76, 70%, 50%)",
        "burger": 46,
        "burgerColor": "hsl(283, 70%, 50%)",
        "sandwich": 43,
        "sandwichColor": "hsl(127, 70%, 50%)",
        "kebab": 96,
        "kebabColor": "hsl(290, 70%, 50%)",
        "fries": 8,
        "friesColor": "hsl(206, 70%, 50%)",
        "donut": 97,
        "donutColor": "hsl(206, 70%, 50%)",
        "junk": 2,
        "junkColor": "hsl(58, 70%, 50%)",
        "sushi": 57,
        "sushiColor": "hsl(239, 70%, 50%)",
        "ramen": 88,
        "ramenColor": "hsl(146, 70%, 50%)",
        "curry": 88,
        "curryColor": "hsl(118, 70%, 50%)",
        "udon": 37,
        "udonColor": "hsl(332, 70%, 50%)",
        "bagel": 46,
        "bagelColor": "hsl(134, 70%, 50%)",
        "yakitori": 18,
        "yakitoriColor": "hsl(86, 70%, 50%)",
        "takoyaki": 20,
        "takoyakiColor": "hsl(85, 70%, 50%)",
        "tacos": 87,
        "tacosColor": "hsl(349, 70%, 50%)",
        "miso soup": 37,
        "miso soupColor": "hsl(16, 70%, 50%)",
        "tortilla": 71,
        "tortillaColor": "hsl(23, 70%, 50%)",
        "tapas": 97,
        "tapasColor": "hsl(245, 70%, 50%)",
        "chipirones": 19,
        "chipironesColor": "hsl(21, 70%, 50%)",
        "gazpacho": 48,
        "gazpachoColor": "hsl(240, 70%, 50%)",
        "soba": 42,
        "sobaColor": "hsl(93, 70%, 50%)",
        "bavette": 78,
        "bavetteColor": "hsl(18, 70%, 50%)",
        "steak": 100,
        "steakColor": "hsl(16, 70%, 50%)",
        "pizza": 46,
        "pizzaColor": "hsl(304, 70%, 50%)",
        "spaghetti": 63,
        "spaghettiColor": "hsl(223, 70%, 50%)",
        "ravioli": 77,
        "ravioliColor": "hsl(160, 70%, 50%)",
        "salad": 23,
        "saladColor": "hsl(48, 70%, 50%)",
        "pad thai": 62,
        "pad thaiColor": "hsl(6, 70%, 50%)",
        "bun": 85,
        "bunColor": "hsl(134, 70%, 50%)",
        "waffle": 53,
        "waffleColor": "hsl(306, 70%, 50%)",
        "crepe": 17,
        "crepeColor": "hsl(143, 70%, 50%)",
        "churros": 86,
        "churrosColor": "hsl(312, 70%, 50%)",
        "paella": 90,
        "paellaColor": "hsl(102, 70%, 50%)",
        "empanadas": 33,
        "empanadasColor": "hsl(279, 70%, 50%)",
        "bruschetta": 92,
        "bruschettaColor": "hsl(47, 70%, 50%)",
        "onion soup": 53,
        "onion soupColor": "hsl(3, 70%, 50%)",
        "cassoulet": 42,
        "cassouletColor": "hsl(258, 70%, 50%)",
        "bouillabaisse": 91,
        "bouillabaisseColor": "hsl(315, 70%, 50%)",
        "unagi": 5,
        "unagiColor": "hsl(130, 70%, 50%)",
        "tempura": 74,
        "tempuraColor": "hsl(121, 70%, 50%)",
        "tonkatsu": 37,
        "tonkatsuColor": "hsl(354, 70%, 50%)",
        "shabu-shabu": 5,
        "shabu-shabuColor": "hsl(89, 70%, 50%)",
        "twinkies": 62,
        "twinkiesColor": "hsl(230, 70%, 50%)",
        "jerky": 59,
        "jerkyColor": "hsl(143, 70%, 50%)",
        "fajitas": 86,
        "fajitasColor": "hsl(123, 70%, 50%)",
        "jambalaya": 39,
        "jambalayaColor": "hsl(48, 70%, 50%)",
        "meatloaf": 6,
        "meatloafColor": "hsl(191, 70%, 50%)",
        "mac n' cheese": 35,
        "mac n' cheeseColor": "hsl(30, 70%, 50%)",
        "baked beans": 0,
        "baked beansColor": "hsl(13, 70%, 50%)",
        "popcorn": 94,
        "popcornColor": "hsl(150, 70%, 50%)",
        "buffalo wings": 18,
        "buffalo wingsColor": "hsl(261, 70%, 50%)",
        "BBQ ribs": 68,
        "BBQ ribsColor": "hsl(44, 70%, 50%)",
        "apple pie": 52,
        "apple pieColor": "hsl(129, 70%, 50%)",
        "nachos": 79,
        "nachosColor": "hsl(140, 70%, 50%)",
        "risotto": 14,
        "risottoColor": "hsl(290, 70%, 50%)",
        "tiramisu": 34,
        "tiramisuColor": "hsl(204, 70%, 50%)"
    },
    {
        "country": "BE",
        "hot dog": 64,
        "hot dogColor": "hsl(4, 70%, 50%)",
        "burger": 85,
        "burgerColor": "hsl(50, 70%, 50%)",
        "sandwich": 28,
        "sandwichColor": "hsl(215, 70%, 50%)",
        "kebab": 24,
        "kebabColor": "hsl(71, 70%, 50%)",
        "fries": 6,
        "friesColor": "hsl(242, 70%, 50%)",
        "donut": 51,
        "donutColor": "hsl(263, 70%, 50%)",
        "junk": 40,
        "junkColor": "hsl(289, 70%, 50%)",
        "sushi": 37,
        "sushiColor": "hsl(298, 70%, 50%)",
        "ramen": 68,
        "ramenColor": "hsl(62, 70%, 50%)",
        "curry": 69,
        "curryColor": "hsl(235, 70%, 50%)",
        "udon": 64,
        "udonColor": "hsl(23, 70%, 50%)",
        "bagel": 8,
        "bagelColor": "hsl(286, 70%, 50%)",
        "yakitori": 90,
        "yakitoriColor": "hsl(88, 70%, 50%)",
        "takoyaki": 31,
        "takoyakiColor": "hsl(173, 70%, 50%)",
        "tacos": 0,
        "tacosColor": "hsl(127, 70%, 50%)",
        "miso soup": 43,
        "miso soupColor": "hsl(264, 70%, 50%)",
        "tortilla": 33,
        "tortillaColor": "hsl(293, 70%, 50%)",
        "tapas": 27,
        "tapasColor": "hsl(215, 70%, 50%)",
        "chipirones": 95,
        "chipironesColor": "hsl(318, 70%, 50%)",
        "gazpacho": 98,
        "gazpachoColor": "hsl(250, 70%, 50%)",
        "soba": 43,
        "sobaColor": "hsl(224, 70%, 50%)",
        "bavette": 77,
        "bavetteColor": "hsl(354, 70%, 50%)",
        "steak": 91,
        "steakColor": "hsl(196, 70%, 50%)",
        "pizza": 37,
        "pizzaColor": "hsl(140, 70%, 50%)",
        "spaghetti": 75,
        "spaghettiColor": "hsl(217, 70%, 50%)",
        "ravioli": 20,
        "ravioliColor": "hsl(280, 70%, 50%)",
        "salad": 33,
        "saladColor": "hsl(291, 70%, 50%)",
        "pad thai": 94,
        "pad thaiColor": "hsl(316, 70%, 50%)",
        "bun": 40,
        "bunColor": "hsl(7, 70%, 50%)",
        "waffle": 84,
        "waffleColor": "hsl(342, 70%, 50%)",
        "crepe": 6,
        "crepeColor": "hsl(143, 70%, 50%)",
        "churros": 82,
        "churrosColor": "hsl(143, 70%, 50%)",
        "paella": 34,
        "paellaColor": "hsl(287, 70%, 50%)",
        "empanadas": 72,
        "empanadasColor": "hsl(246, 70%, 50%)",
        "bruschetta": 2,
        "bruschettaColor": "hsl(73, 70%, 50%)",
        "onion soup": 89,
        "onion soupColor": "hsl(126, 70%, 50%)",
        "cassoulet": 68,
        "cassouletColor": "hsl(24, 70%, 50%)",
        "bouillabaisse": 12,
        "bouillabaisseColor": "hsl(135, 70%, 50%)",
        "unagi": 57,
        "unagiColor": "hsl(228, 70%, 50%)",
        "tempura": 59,
        "tempuraColor": "hsl(154, 70%, 50%)",
        "tonkatsu": 1,
        "tonkatsuColor": "hsl(120, 70%, 50%)",
        "shabu-shabu": 8,
        "shabu-shabuColor": "hsl(123, 70%, 50%)",
        "twinkies": 2,
        "twinkiesColor": "hsl(74, 70%, 50%)",
        "jerky": 39,
        "jerkyColor": "hsl(127, 70%, 50%)",
        "fajitas": 74,
        "fajitasColor": "hsl(81, 70%, 50%)",
        "jambalaya": 35,
        "jambalayaColor": "hsl(257, 70%, 50%)",
        "meatloaf": 40,
        "meatloafColor": "hsl(308, 70%, 50%)",
        "mac n' cheese": 74,
        "mac n' cheeseColor": "hsl(185, 70%, 50%)",
        "baked beans": 67,
        "baked beansColor": "hsl(267, 70%, 50%)",
        "popcorn": 39,
        "popcornColor": "hsl(239, 70%, 50%)",
        "buffalo wings": 33,
        "buffalo wingsColor": "hsl(194, 70%, 50%)",
        "BBQ ribs": 9,
        "BBQ ribsColor": "hsl(164, 70%, 50%)",
        "apple pie": 31,
        "apple pieColor": "hsl(77, 70%, 50%)",
        "nachos": 59,
        "nachosColor": "hsl(28, 70%, 50%)",
        "risotto": 63,
        "risottoColor": "hsl(98, 70%, 50%)",
        "tiramisu": 67,
        "tiramisuColor": "hsl(228, 70%, 50%)"
    },
    {
        "country": "BF",
        "hot dog": 1,
        "hot dogColor": "hsl(255, 70%, 50%)",
        "burger": 11,
        "burgerColor": "hsl(225, 70%, 50%)",
        "sandwich": 10,
        "sandwichColor": "hsl(98, 70%, 50%)",
        "kebab": 83,
        "kebabColor": "hsl(277, 70%, 50%)",
        "fries": 93,
        "friesColor": "hsl(256, 70%, 50%)",
        "donut": 29,
        "donutColor": "hsl(83, 70%, 50%)",
        "junk": 2,
        "junkColor": "hsl(162, 70%, 50%)",
        "sushi": 76,
        "sushiColor": "hsl(147, 70%, 50%)",
        "ramen": 18,
        "ramenColor": "hsl(85, 70%, 50%)",
        "curry": 53,
        "curryColor": "hsl(232, 70%, 50%)",
        "udon": 4,
        "udonColor": "hsl(300, 70%, 50%)",
        "bagel": 84,
        "bagelColor": "hsl(22, 70%, 50%)",
        "yakitori": 55,
        "yakitoriColor": "hsl(152, 70%, 50%)",
        "takoyaki": 1,
        "takoyakiColor": "hsl(273, 70%, 50%)",
        "tacos": 71,
        "tacosColor": "hsl(148, 70%, 50%)",
        "miso soup": 67,
        "miso soupColor": "hsl(261, 70%, 50%)",
        "tortilla": 11,
        "tortillaColor": "hsl(101, 70%, 50%)",
        "tapas": 32,
        "tapasColor": "hsl(216, 70%, 50%)",
        "chipirones": 13,
        "chipironesColor": "hsl(109, 70%, 50%)",
        "gazpacho": 24,
        "gazpachoColor": "hsl(329, 70%, 50%)",
        "soba": 13,
        "sobaColor": "hsl(25, 70%, 50%)",
        "bavette": 72,
        "bavetteColor": "hsl(313, 70%, 50%)",
        "steak": 35,
        "steakColor": "hsl(170, 70%, 50%)",
        "pizza": 30,
        "pizzaColor": "hsl(14, 70%, 50%)",
        "spaghetti": 59,
        "spaghettiColor": "hsl(96, 70%, 50%)",
        "ravioli": 66,
        "ravioliColor": "hsl(181, 70%, 50%)",
        "salad": 96,
        "saladColor": "hsl(326, 70%, 50%)",
        "pad thai": 93,
        "pad thaiColor": "hsl(304, 70%, 50%)",
        "bun": 16,
        "bunColor": "hsl(231, 70%, 50%)",
        "waffle": 89,
        "waffleColor": "hsl(356, 70%, 50%)",
        "crepe": 55,
        "crepeColor": "hsl(309, 70%, 50%)",
        "churros": 94,
        "churrosColor": "hsl(194, 70%, 50%)",
        "paella": 21,
        "paellaColor": "hsl(338, 70%, 50%)",
        "empanadas": 62,
        "empanadasColor": "hsl(184, 70%, 50%)",
        "bruschetta": 6,
        "bruschettaColor": "hsl(161, 70%, 50%)",
        "onion soup": 75,
        "onion soupColor": "hsl(278, 70%, 50%)",
        "cassoulet": 22,
        "cassouletColor": "hsl(207, 70%, 50%)",
        "bouillabaisse": 41,
        "bouillabaisseColor": "hsl(204, 70%, 50%)",
        "unagi": 79,
        "unagiColor": "hsl(292, 70%, 50%)",
        "tempura": 78,
        "tempuraColor": "hsl(52, 70%, 50%)",
        "tonkatsu": 46,
        "tonkatsuColor": "hsl(158, 70%, 50%)",
        "shabu-shabu": 76,
        "shabu-shabuColor": "hsl(328, 70%, 50%)",
        "twinkies": 93,
        "twinkiesColor": "hsl(13, 70%, 50%)",
        "jerky": 29,
        "jerkyColor": "hsl(64, 70%, 50%)",
        "fajitas": 97,
        "fajitasColor": "hsl(210, 70%, 50%)",
        "jambalaya": 95,
        "jambalayaColor": "hsl(238, 70%, 50%)",
        "meatloaf": 17,
        "meatloafColor": "hsl(157, 70%, 50%)",
        "mac n' cheese": 11,
        "mac n' cheeseColor": "hsl(77, 70%, 50%)",
        "baked beans": 1,
        "baked beansColor": "hsl(177, 70%, 50%)",
        "popcorn": 95,
        "popcornColor": "hsl(163, 70%, 50%)",
        "buffalo wings": 88,
        "buffalo wingsColor": "hsl(197, 70%, 50%)",
        "BBQ ribs": 65,
        "BBQ ribsColor": "hsl(249, 70%, 50%)",
        "apple pie": 88,
        "apple pieColor": "hsl(255, 70%, 50%)",
        "nachos": 34,
        "nachosColor": "hsl(207, 70%, 50%)",
        "risotto": 75,
        "risottoColor": "hsl(260, 70%, 50%)",
        "tiramisu": 77,
        "tiramisuColor": "hsl(149, 70%, 50%)"
    },
    {
        "country": "BG",
        "hot dog": 4,
        "hot dogColor": "hsl(335, 70%, 50%)",
        "burger": 41,
        "burgerColor": "hsl(291, 70%, 50%)",
        "sandwich": 6,
        "sandwichColor": "hsl(81, 70%, 50%)",
        "kebab": 14,
        "kebabColor": "hsl(99, 70%, 50%)",
        "fries": 55,
        "friesColor": "hsl(134, 70%, 50%)",
        "donut": 56,
        "donutColor": "hsl(269, 70%, 50%)",
        "junk": 63,
        "junkColor": "hsl(176, 70%, 50%)",
        "sushi": 60,
        "sushiColor": "hsl(259, 70%, 50%)",
        "ramen": 29,
        "ramenColor": "hsl(2, 70%, 50%)",
        "curry": 1,
        "curryColor": "hsl(345, 70%, 50%)",
        "udon": 77,
        "udonColor": "hsl(182, 70%, 50%)",
        "bagel": 12,
        "bagelColor": "hsl(44, 70%, 50%)",
        "yakitori": 54,
        "yakitoriColor": "hsl(141, 70%, 50%)",
        "takoyaki": 17,
        "takoyakiColor": "hsl(254, 70%, 50%)",
        "tacos": 55,
        "tacosColor": "hsl(114, 70%, 50%)",
        "miso soup": 86,
        "miso soupColor": "hsl(38, 70%, 50%)",
        "tortilla": 33,
        "tortillaColor": "hsl(273, 70%, 50%)",
        "tapas": 80,
        "tapasColor": "hsl(317, 70%, 50%)",
        "chipirones": 17,
        "chipironesColor": "hsl(256, 70%, 50%)",
        "gazpacho": 22,
        "gazpachoColor": "hsl(327, 70%, 50%)",
        "soba": 52,
        "sobaColor": "hsl(322, 70%, 50%)",
        "bavette": 14,
        "bavetteColor": "hsl(140, 70%, 50%)",
        "steak": 50,
        "steakColor": "hsl(104, 70%, 50%)",
        "pizza": 99,
        "pizzaColor": "hsl(290, 70%, 50%)",
        "spaghetti": 24,
        "spaghettiColor": "hsl(165, 70%, 50%)",
        "ravioli": 38,
        "ravioliColor": "hsl(79, 70%, 50%)",
        "salad": 58,
        "saladColor": "hsl(102, 70%, 50%)",
        "pad thai": 97,
        "pad thaiColor": "hsl(140, 70%, 50%)",
        "bun": 9,
        "bunColor": "hsl(244, 70%, 50%)",
        "waffle": 90,
        "waffleColor": "hsl(92, 70%, 50%)",
        "crepe": 36,
        "crepeColor": "hsl(67, 70%, 50%)",
        "churros": 21,
        "churrosColor": "hsl(298, 70%, 50%)",
        "paella": 89,
        "paellaColor": "hsl(352, 70%, 50%)",
        "empanadas": 15,
        "empanadasColor": "hsl(207, 70%, 50%)",
        "bruschetta": 42,
        "bruschettaColor": "hsl(81, 70%, 50%)",
        "onion soup": 34,
        "onion soupColor": "hsl(68, 70%, 50%)",
        "cassoulet": 37,
        "cassouletColor": "hsl(337, 70%, 50%)",
        "bouillabaisse": 68,
        "bouillabaisseColor": "hsl(332, 70%, 50%)",
        "unagi": 20,
        "unagiColor": "hsl(156, 70%, 50%)",
        "tempura": 94,
        "tempuraColor": "hsl(32, 70%, 50%)",
        "tonkatsu": 42,
        "tonkatsuColor": "hsl(110, 70%, 50%)",
        "shabu-shabu": 11,
        "shabu-shabuColor": "hsl(78, 70%, 50%)",
        "twinkies": 19,
        "twinkiesColor": "hsl(330, 70%, 50%)",
        "jerky": 62,
        "jerkyColor": "hsl(313, 70%, 50%)",
        "fajitas": 70,
        "fajitasColor": "hsl(265, 70%, 50%)",
        "jambalaya": 53,
        "jambalayaColor": "hsl(326, 70%, 50%)",
        "meatloaf": 31,
        "meatloafColor": "hsl(184, 70%, 50%)",
        "mac n' cheese": 17,
        "mac n' cheeseColor": "hsl(173, 70%, 50%)",
        "baked beans": 85,
        "baked beansColor": "hsl(104, 70%, 50%)",
        "popcorn": 38,
        "popcornColor": "hsl(259, 70%, 50%)",
        "buffalo wings": 79,
        "buffalo wingsColor": "hsl(108, 70%, 50%)",
        "BBQ ribs": 90,
        "BBQ ribsColor": "hsl(161, 70%, 50%)",
        "apple pie": 11,
        "apple pieColor": "hsl(95, 70%, 50%)",
        "nachos": 26,
        "nachosColor": "hsl(88, 70%, 50%)",
        "risotto": 88,
        "risottoColor": "hsl(66, 70%, 50%)",
        "tiramisu": 13,
        "tiramisuColor": "hsl(6, 70%, 50%)"
    }
]